{"data":[{"name":"House Cargyll","coatOfArms":" Bendy sinister sable and gules, a goose Or","currentLord":" extinct","region":"Crownlands","overlord":"House Targaryen","died out":"209 AC"},{"name":"House Redfort","coatOfArms":" A red castle, on a white field, within a red embattled border<br>(<i>Argent, a castle within a bordure embattled gules</i>)","words":" <i>As Strong as Stone</i>","seat":"Redfort","currentLord":"Horton Redfort","region":"The Vale","title":"Redfort","overlord":"House Arryn"},{"name":"House Lannister","coatOfArms":" A gold lion, on a crimson field<br>(<i>Gules, a lion or</i>)","words":" <i>Hear Me Roar!</i>","seat":"Casterly Rock","currentLord":"Cersei Lannister","region":"Westerlands","title":"King of the Rock","overlord":"House Baratheon of King's Landing","cadetBranch":"House Lannister of Lannisport","ancestralWeapon":"Brightroar","founder":"Lann the Clever","founded":"Age of Heroes"},{"name":"House Tyrell","coatOfArms":" Vert, a rose Or","words":" <i>Growing Strong</i>","seat":"Highgarden","currentLord":"Mace Tyrell","region":"Reach","title":"Highgarden","heir":"Willas Tyrell","overlord":"House Baratheon of King's Landing","cadetBranch":"House Tyrell of Brightwater Keep","founder":"Alester Tyrell"},{"name":"House Mooton","coatOfArms":" A red salmon within a gold tressure, on a white field<br>(<i>Argent, a salmon gules within a tressure or</i>)","words":" <i>Wisdom and Strength</i>","seat":"Maidenpool","currentLord":"William Mooton","region":"Riverlands","title":" Lord of Maidenpool","overlord":"House Baelish of Harrenhal"},{"name":"House Merryweather","coatOfArms":" White, a cornucopia Or spilling foods proper within a bordure Or","words":" <i>Behold Our Bounty</i>","seat":"Longtable","currentLord":"Orton Merryweather","region":"the Reach","heir":"Russell Merryweather","overlord":"House Tyrell"},{"name":"House Moreland","coatOfArms":" Per pale barry russet and green<br>(<i>Per pale barry tenné and vert</i>)","currentLord":"Robin Moreland","region":"Westerlands","overlord":"House Lannister","founder":"Pate the Plowman"},{"name":"House Mallister","coatOfArms":" A silver eagle, displayed, on an indigo field<br>(<i>Purpure, an eagle displayed argent</i>)","words":" <i>Above the Rest</i>","seat":"Seagard","currentLord":"Jason Mallister","region":"Riverlands","title":" Lord of Seagard","heir":"Patrek Mallister","overlord":"House Baelish of Harrenhal"},{"name":"House Waynwood","coatOfArms":" A broken black wheel, on a green field<br>(<i>Vert, a wheel broken sable</i>)","seat":"Ironoaks","currentLord":"Anya Waynwood","region":"The Vale","title":"Ironoaks","heir":"Morton Waynwood","overlord":"House Arryn"},{"name":"House Volmark","coatOfArms":" Cendrée, a leviathan sable","seat":"Volmark","currentLord":"Maron Volmark","region":"Iron Islands","title":" Lord of Volmark<br>Lord of Greenshield","overlord":"House Harlaw"},{"name":"House Manwoody","coatOfArms":" Sable, a skull argent crowned or.","seat":"Kingsgrave","currentLord":"Dagos Manwoody","region":"Dorne","heir":"Mors Manwoody","overlord":"House Martell"},{"name":"House Marbrand","coatOfArms":" An orange burning tree, on a smoky field<br>(<i>Cendrée, a tree in flame tenné</i>)","words":" <i>Burning bright</i>","seat":"Ashemark","currentLord":"Damon Marbrand","region":"Westerlands","title":"Ashemark","heir":"Addam Marbrand","overlord":"House Lannister"},{"name":"House Templeton","coatOfArms":" Nine stars, one of seven points and eight of six points, on a gold saltire, on a black field<br>(<i>Sable, on a saltire or, nine mullets of the field, that in fesse-point of seven points, all others of six points</i>)","seat":"Ninestars","currentLord":"Ser","title":"Knight of Ninestars","overlord":"House Arryn"},{"name":"House Manderly","coatOfArms":" A white merman with dark green hair, beard and tail, carrying a black trident, on a blue-green field","seat":"New Castle","currentLord":"Wyman Manderly","region":"North","title":"White Harbor","heir":"Wylis Manderly","overlord":"House Bolton"},{"name":"House Redwyne","coatOfArms":" Azure, a grape cluster proper","seat":"Arbor","currentLord":"Paxter Redwyne","region":"Reach","title":"Arbor","heir":"Horas Redwyne","overlord":"House Tyrell","founder":"Gilbert of the Vines"},{"name":"House Mormont","coatOfArms":" A wood vert, a bear sable","words":" <i>Here We Stand</i>","seat":"Bear Island","currentLord":"Maege Mormont","region":"The North","title":"Bear Island","heir":"Alysane Mormont","overlord":"House Stark","ancestralWeapon":"Longclaw"},{"name":"House Morrigen","coatOfArms":" A black crow in flight on a storm-green field<br>(<i>Vert, a crow volant sable</i>)","seat":"Crow's Nest","currentLord":"Lester Morrigen","region":"Stormlands","title":" Lord of Crow's Nest","heir":"Richard Morrigen","overlord":"House Baratheon"},{"name":"House Florent","coatOfArms":" A red fox in a circle of blue flowers on ermine","seat":"Brightwater Keep","currentLord":"Alekyne Florent","region":"The Reach","title":"Brightwater","heir":"Melessa Florent","overlord":"House Baratheon of Dragonstone","founder":"Florys the Fox"},{"name":"House Stark","coatOfArms":" A running grey direwolf, on an ice-white field","words":" <i>Winter is Coming</i>","seat":"Winterfell","currentLord":" unknown","region":"North","title":"King in the North","overlord":"House Baratheon of King's Landing","cadetBranch":"House Greystark","ancestralWeapon":"Ice","founder":"Bran the Builder","founded":"Age of Heroes"},{"name":"House Greyjoy","coatOfArms":" Sable, a kraken Or","words":" <i>We Do Not Sow</i>","seat":"Pyke","currentLord":"Euron Greyjoy","region":"Iron Islands","title":"Lord Reaper of Pyke","heir":"Theon Greyjoy","overlord":"sovereign","founded":"Age of Heroes"},{"name":"House Whent","coatOfArms":" Nine black bats, on a yellow field<br>(<i>Or, nine bats, 4, 3, 2, displayed sable</i>)","seat":"Harrenhal","currentLord":" <i>Extinct</i>","region":"Riverlands","title":"Lord of Harrenhal","overlord":"House Tully"},{"name":"House Bolton","coatOfArms":" A red flayed man on pink de sang","words":" <i>Our Blades are Sharp</i>","seat":"Dreadfort","currentLord":"Roose Bolton","region":"north","title":"Red King","heir":"Ramsay Bolton","overlord":"House Baratheon of King's Landing","cadetBranch":"House Bolton of Winterfell","founded":"Age of Heroes"},{"name":"House Hornwood","coatOfArms":" Tenny, a bull moose trippant proper","words":" <i>Righteous in Wrath</i>","seat":"Hornwood","region":"North","title":"Lord of the Hornwood","overlord":"House Stark"},{"name":"House Hightower","coatOfArms":" Cendrée, a tower argent with a beacon on fire gules","words":" <i>We Light the Way</i>","seat":"Hightower","currentLord":"Leyton Hightower","region":"Reach","title":"Lord of the Hightower","heir":"Baelor Hightower","overlord":"House Tyrell","ancestralWeapon":"Vigilance","founder":"Uthor of the High Tower","founded":"Age of Dawn"},{"name":"House Parren","coatOfArms":" Per saltire: burgundy and white stripes; a black lion's head on a gold field<br>(<i>Per saltire, the first paly gules and argent, the second or, a lion's head erased sable</i>)","currentLord":" Extinct","region":"the Westerlands","overlord":"House Lannister","died out":"209 AC"},{"name":"House Penrose","coatOfArms":" White crossed quills, on a russet field<br>(<i>Tenné, two quills saltirewise argent</i>)","words":" <i>Set Down Our Deeds</i>","seat":"Parchments","region":"The Stormlands","title":"Parchments","overlord":"House Baratheon"},{"name":"House Orkwood","coatOfArms":" Or, semy of pines vert","seat":"Orkmont","region":"Iron Islands","overlord":"House Greyjoy"},{"name":"House Reed","coatOfArms":" Vert, a lizard-lion sable","seat":"Greywater Watch","currentLord":"Howland Reed","region":"The Neck","heir":"Jojen Reed","overlord":"House Stark"},{"name":"House Royce of the Gates of the Moon","coatOfArms":" A black portcullis over a white crescent moon, on a purple field, bordered with runes on bronze<br>(<i>Purpure, a moon increscent argent surmounted by a portcullis sable, all within a bordure tenné charged with ancient runes of the third</i>)","seat":"Gates of the Moon","currentLord":"Nestor Royce","region":"Vale","title":" Lord of the Gates of the Moon","heir":"Albar Royce","overlord":"House Arryn"},{"name":"House Paege","coatOfArms":" Twining red-and-white snakes, on a black field<br>(<i>Sable, two serpents argent and gules entwined palewise</i>)","currentLord":"Halmon Paege","region":"Riverlands","overlord":"House Baelish of Harrenhal"},{"name":"House Dayne","coatOfArms":" A white sword and falling star crossed on lilac (<i>Purpure, a blazing star bendways surmounted by a sword bendways sinister argent</i>)","seat":"Starfall","currentLord":"Edric Dayne","region":"Dorne","title":"Lord of Starfall","overlord":"House Martell","cadetBranch":"House Dayne of High Hermitage","ancestralWeapon":"Dawn"},{"name":"House Baratheon","coatOfArms":" A black crowned stag, on a gold field<br>(<i>Or, a stag salient, crowned, sable</i>)","words":" <i>Ours is the Fury</i>","seat":"Storm's End","currentLord":"Tommen I","region":"Stormlands","title":"Storm's End","heir":"Myrcella","overlord":"Baratheons of King's Landing","cadetBranch":"Baratheons of King's Landing","founder":"Orys Baratheon","founded":"1 AC"},{"name":"House Tarth","coatOfArms":" Quartered, yellow sun on a rose-coloured field and white crescents on a blue field<br>(<i>Quarterly, first and fourth, carnation, a sun-in-splendour or, second and third, azure, a moon increscent argent</i>)","seat":"Evenfall Hall","currentLord":"Selwyn Tarth","region":"Stormlands","title":"Tarth","heir":"Brienne of Tarth","overlord":"House Baratheon"},{"name":"House Clegane","coatOfArms":" Three dogs on a yellow field<br>(<i>Or, three dogs courant in pale sable</i>)","seat":"Clegane's Keep","currentLord":" Extinct","region":"the Westerlands","title":" Ser","overlord":"House Lannister","founder":"Clegane"},{"name":"House Waxley","coatOfArms":" Three candles, white with red flames, within silver candle holders, on a grey field within a black border<br>(<i>Cendrée, three candles in holders argent, flamed gules, within a bordure sable</i>)","words":" <i>Light in Darkness</i>","seat":"Wickenden","currentLord":"Edmund Waxley","region":"The Vale","title":" The Knight of Wickenden","overlord":"House Arryn"},{"name":"House Baratheon of Dragonstone","coatOfArms":" Or, a heart gules enflamed proper charged with a stag's head sable crowned of the field","seat":"Dragonstone","currentLord":"Stannis I","region":"Crownlands","title":"King of Westeros","heir":"Shireen Baratheon","overlord":"sovereign","founder":"Stannis Baratheon","founded":"284 AC"},{"name":"House Baratheon of King's Landing","coatOfArms":" A black crowned stag and a gold lion, combatant, on a per pale gold and crimson field<br>(<i>Per pale or and gules, a stag, crowned, sable and a lion of the first combatant</i>)","seat":"Red Keep","currentLord":"Tommen of House Baratheon","region":"Crownlands","heir":"Myrcella Baratheon","overlord":"sovereign","founder":"Robert I Baratheon","founded":"283 AC"},{"name":"House Mullendore","coatOfArms":" Black-and-orange butterflies on white","seat":"Uplands","currentLord":"Martyn Mullendore","region":"the Reach","title":" Lord of Uplands","overlord":"House Hightower"},{"name":"House Gargalen","coatOfArms":" Or, a cockatrice gules, in its beak a serpent sable","seat":"Salt Shore","currentLord":"Tremond Gargalen","region":"Dorne","title":" Lord of Salt Shore","overlord":"House Martell"},{"name":"House Westerling","coatOfArms":" Six white shells, on a sand-coloured field<br>(<i>Or, six escallops argent</i>)","words":" <i>Honor, Not Honors</i>","seat":"Crag","currentLord":"Gawen Westerling","region":"Westerlands","title":"Crag","heir":"Rollam Westerling","overlord":"House Lannister"},{"name":"House Martell","coatOfArms":" Tenny, a sun in splendour gules transfixed by a spear bendwise Or","words":" <i>Unbowed, Unbent, Unbroken</i>","seat":"Old Palace","currentLord":"Doran Martell","region":"Dorne","title":"Sandship","heir":"Arianne Martell","overlord":"House Baratheon of King's Landing","founder":"Morgan Martell","founded":" 1,000 years ago"},{"name":"House Umber","coatOfArms":" Gules, a roaring giant proper with shattered chains argent","seat":"Last Hearth","currentLord":"Jon \"Greatjon\" Umber","region":"The North","title":"Last Hearth","overlord":"House Stark"},{"name":"House Uller","coatOfArms":" per fess rayonny Or and gules","seat":"Hellholt","currentLord":"Harmen Uller","region":"Dorne","title":" Lord of Hellholt","overlord":"House Martell"},{"name":"House Royce","coatOfArms":" Black iron studs on a bronze field, bordered with runes<br>(<i>Tenné pelletée, an orle of ancient runes sable</i>)","words":" <i>We Remember</i>","seat":"Runestone","currentLord":"Yohn Royce","region":"The Vale","title":"High King of the Vale, the Fingers and the Mountains of the Moon","heir":"Andar Royce","overlord":"House Arryn","cadetBranch":"Royce of the Gates of the Moon","ancestralWeapon":"Lamentation","founded":"Age of Heroes"},{"name":"House Tarly","coatOfArms":" Vert, a huntsman striding to dexter proper garbed gules","words":" <i>First in Battle</i>","seat":"Horn Hill","currentLord":"Randyll Tarly","region":"The Reach","title":" Lord of Horn Hill","heir":"Dickon Tarly","overlord":"House Tyrell","ancestralWeapon":"Heartsbane"},{"name":"House Oakheart","coatOfArms":" Or, three oak leaves vert","words":" <i>Our Roots Go Deep</i>","seat":"Old Oak","currentLord":"Arwyn Oakheart","region":"The Reach","overlord":"House Tyrell","founder":"John the Oak"},{"name":"House Piper","coatOfArms":" A pink dancing maiden in a swirl of white silk, on a blue field<br>(<i>Azure, a maiden dancing proper enwrapped with silk argent</i>)","words":" <i>Brave and Beautiful</i>","seat":"Pinkmaiden Castle","currentLord":"Clement Piper","region":"Riverlands","heir":"Marq Piper","overlord":"House Baelish of Harrenhal"},{"name":"House Plumm","coatOfArms":" Three purple roundels, on a gold field<br>(<i>Or, three golpes</i>)","words":" <i>Come Try Me</i>","currentLord":"Philip Plumm","region":"Westerlands","heir":"Dennis Plumm","overlord":"House Lannister"},{"name":"House Prester","coatOfArms":" A red ox, on an ermine field<br>(<i>Ermine, an ox passant gules</i>)","words":" <i>Tireless</i>","seat":"Feastfires","currentLord":"Garrison Prester","region":"Westerlands","title":" Lord of Feastfires","overlord":"House Lannister"},{"name":"House Qorgyle","coatOfArms":" Gules, three scorpions sable.","seat":"Sandstone","currentLord":"Quentyn Qorgyle","region":"Dorne","title":" Lord of Sandstone","heir":"Gulian Qorgyle","overlord":"House Martell"},{"name":"House Swann","coatOfArms":" Battling swans black and white, beaks and feet golden, on per pale white and black field<br>(<i>Per pale argent and sable, two swans combatant counterchanged, beaked and membered or</i>)","seat":"Stonehelm","currentLord":"Gulian Swann","region":"Stormlands","title":" Lord of Stonehelm","heir":"Donnel Swann","overlord":"House Baratheon"},{"name":"House Sunglass","coatOfArms":" Argent, seven mullets of seven points or","seat":"Sweetport Sound","currentLord":" Lord Sunglass","region":"Blackwater Bay","title":"Lord","overlord":"House Baratheon of Dragonstone"},{"name":"House Rosby","coatOfArms":" Ermine, three chevronels gules","seat":"Rosby","currentLord":"Gyles Rosby","region":"Crownlands","title":"Rosby","overlord":"House Baratheon of King's Landing"},{"name":"House Corbray","coatOfArms":" Three black ravens in flight, holding three red hearts, on a white field<br>(<i>Argent, three ravens volant sable, each clutching in their claws a heart gules</i>)","seat":"Heart's Home","currentLord":"Lyonel Corbray","title":"King of the Fingers","heir":"Lyn Corbray","overlord":"House Arryn","ancestralWeapon":"Lady Forlorn","founder":"Corwyn Cobray"},{"name":"House Ruttiger","coatOfArms":" An orange engrailed bend, on a black field<br>(<i>Sable, a bend tenné engrailed</i>)","currentLord":"Raynard Ruttiger","region":"the Westerlands","overlord":"House Lannister"},{"name":"House Rowan","coatOfArms":" Argent, a tree eradicated","seat":"Goldengrove","currentLord":"Mathis Rowan","region":"Reach","title":"Goldengrove","overlord":"House Tyrell","founder":"Rowan Gold-Tree"},{"name":"House Saltcliffe","coatOfArms":" Argent, a serpent nine-headed sable","seat":"Saltcliffe","currentLord":"Donnor Saltcliffe","region":"Iron Islands","overlord":"House Greyjoy"},{"name":"House Tawney","coatOfArms":" A scourge of nettles, red and black, on white","seat":"Orkmont","region":"Iron Islands","overlord":"House Greyjoy"},{"name":"House Ryswell","coatOfArms":" Bronze, a horse's head sable orbed and maned gules within a bordure engrailed sable","currentLord":"Rodrik Ryswell","region":"North","title":"Rills","overlord":"House Bolton"},{"name":"House Frey","coatOfArms":" Two blue towers, united by a bridge, on a silver-grey field<br>(<i>Cendrée, a bridge azure, at either end a tower of the same</i>)","seat":"Twins","currentLord":"Walder Frey","region":"riverlands","title":"Lord of the Crossing","heir":"Edwyn Frey","overlord":"House Baelish of Harrenhal","cadetBranch":"House Frey of Riverrun","founded":" 600 years ago"},{"name":"House Serry","coatOfArms":" Argent, an escutcheon gules charged with a rose of the first all within a bordure embattled of the second","seat":"Southshield","currentLord":"Osbert Serry","region":"Shield Islands","heir":"Talbert Serry","overlord":"House Tyrell"},{"name":"House Stackspear","coatOfArms":" Two crossed black spears, on a checkered silver and gold field<br>(<i>Chequy argent and or, two spears in saltire sable</i>)","currentLord":"Selmond Stackspear","region":"the Westerlands","heir":"Steffon Stackspear","overlord":"House Lannister"},{"name":"House Sparr","coatOfArms":" an oak saltire on blue","seat":"Great Wyk","currentLord":"The Sparr","region":"Iron Islands","overlord":"House Greyjoy"},{"name":"House Staedmon","coatOfArms":" A black dagger piercing a red heart on a white de sang field, within an undulating red border<br>(<i>Argent goutté-de-sang, a heart gules transfixed by a dagger sable, all within a bordure wavy of the second</i>)","seat":"Broad Arch","currentLord":"Alesander Staedmon","region":"the Stormlands","overlord":"House Baratheon"},{},{"name":"House Arryn","coatOfArms":" A sky-blue falcon soaring against a white moon, on a sky-blue field<br>(<i>Bleu celeste, upon a plate a falcon volant of the field</i>)","words":" <i>As High as Honor</i>","seat":"Eyrie","currentLord":"Robert Arryn","region":"Vale of Arryn","title":"King of Mountain and Vale","heir":"Harrold Hardyng","overlord":"House Baratheon of King's Landing","cadetBranch":"House Arryn of Gulltown","founder":"Artys Arryn","founded":"Coming of the Andals"},{"name":"House Tully","coatOfArms":" A leaping silver trout on a field of blue and mud red<br>(<i>Paly wavy azure and gules, a trout embowed argent</i>)","words":" <i>Family, Duty, Honor</i>","seat":"Riverrun","currentLord":"Edmure Tully","region":"Riverlands","title":"Riverrun","heir":"Roslin Frey","overlord":"House Stark"},{"name":"House Sunderly","coatOfArms":" A drowned man, pink and pale, floating upright in a blue-green sea","region":"Iron Islands","overlord":"House Greyjoy"},{"name":"House Stokeworth","coatOfArms":" Vert, a lamb couchant argent holding a goblet or","words":" <i>Proud to be Faithful</i>","seat":"Stokeworth","currentLord":"Lollys Stokeworth","region":"Crownlands","title":" Lord of Stokeworth","heir":"Tyrion Tanner","overlord":"House Baratheon of King's Landing"},{"name":"House Sunderland","coatOfArms":" Three women's heads, white with black hair, on a barry wavy blue and green field<br>(<i>Barry wavy azure and vert, three women's heads argents, crined sable</i>)","seat":"Sisterton","currentLord":"Triston Sunderland","region":"Vale of Arryn","title":"Three Sisters","overlord":"House Arryn"},{"name":"House Stonehouse","coatOfArms":" a black brazier on a grey masonry field","seat":"Old Wyk","currentLord":"The Stonehouse","region":"Iron Islands","overlord":"House Greyjoy"},{"name":"House Santagar","coatOfArms":" Per bend sinister azure and argent, a leopard rampant Or spotted sable bearing an axe of the third","seat":"Spottswood","currentLord":"Symon Santagar","region":"Dorne","title":" the Knight of Spottswood","heir":"Sylva Santagar","overlord":"House Martell","founded":"Andal Invasion"},{"name":"House Swyft","coatOfArms":" A blue bantam rooster, on a yellow field<br>(<i>Or, a cock close azure</i>)","words":" <i>Awake! Awake!</i>","seat":"Cornfield","currentLord":"Harys Swyft","region":"Westerlands","title":"Knight","heir":"Steffon Swyft","overlord":"House Lannister"},{},{"name":"House Tollett","coatOfArms":" Pily grey and black<br>(<i>Pily cendrée and sable</i>)","words":" <i>When All is Darkest</i>","seat":"Grey Glen","currentLord":"Uthor Tollett","region":"The Vale","title":"Grey Glen","overlord":"House Royce"},{"name":"House Vance of Atranta","coatOfArms":" Quartered, a green dragon on a white field and a white tower on a black field<br>(<i>Quarterly, first and fourth, argent, a dragon vert, second and third, sable, a tower argent</i>)","seat":"Atranta","currentLord":"Norbert Vance","region":"Riverlands","heir":"Ronald Vance","overlord":"House Baelish of Harrenhal","founder":"Armistead Vance"},{"name":"House Toland","coatOfArms":" Or, a dragon biting its tail vert","seat":"Ghost Hill","currentLord":"Nymella Toland","region":"Dorne","overlord":"House Martell"},{"name":"House Velaryon","coatOfArms":" seahorse rampant argent, on sea green","words":" <i>The Old, the True, the Brave</i>","seat":"High Tide","currentLord":"Monterys Velaryon","region":"Blackwater Bay","title":"Lord of the Tides","overlord":"House Baratheon of Dragonstone","founded":"114BC"},{"name":"House Tallhart","coatOfArms":" Tenny, three sentinel trees vert","words":" <i>Proud and Free</i>","seat":"Torrhen's Square","currentLord":"Eddara Tallhart","region":"North","title":" Master of Torrhen's Square","heir":"Brandon Tallhart","overlord":"House Bolton"},{},{"name":"House Norrey","coatOfArms":" Or,six thistles slipped vert","currentLord":"Brandon Norrey","region":"The North","title":" The Norrey<br>Lord Norrey","overlord":"House Stark"},{"name":"House Vikary","coatOfArms":" Quarterly: a red boar's head on a white field; beneath a gold bend sinister, a silver lion rampant regardant with a forked tail, with gold teeth and claws, on a red field<br>(<i>Quarterly, first and fourth, argent, a boar's head couped gules, second and third, gules, a lion rampant regardant queue-forché argent, armed and langued or, debruised by a bend sinister of the last</i>)","currentLord":"Lymond Vikary","region":"Westerlands","overlord":"House Lannister"},{"name":"House Targaryen","coatOfArms":" Sable, a dragon thrice-headed gules","words":" <i>Fire and Blood</i>","seat":"Red Keep","currentLord":"Daenerys Targaryen","region":"Crownlands","title":"King","overlord":" None","cadetBranch":"House Blackfyre","ancestralWeapon":"Blackfyre","founded":"126 BC"},{"name":"House Wull","coatOfArms":" Azure, three wooden buckets tenné, a bordure chequy cendrée and white","currentLord":"Hugo Wull","region":"North","title":" The Wull <br> Lord Wull","overlord":"House Stark"},{"name":"House Wynch","coatOfArms":" a bloody moon on purple","seat":"Iron Holt","currentLord":"Waldon Wynch","region":"Iron Islands","title":" Lord of Iron Holt","overlord":"House Greyjoy"},{"name":"House Yew","coatOfArms":" A golden longbow between two crimson flaunches, on a white field<br>(<i>Argent, a longbow or between two flaunches gules</i>)","currentLord":"Manfryd Yew","region":"Westerlands","overlord":"House Lannister","founder":"Alan o' the Oak"},{"name":"House Burley","coatOfArms":" White, upon a pile azure a knife white","region":"North","overlord":"House Bolton"},{"name":"House Yronwood","coatOfArms":" Or, a portcullis sable","words":" <i>We Guard the Way</i>","seat":"Yronwood","currentLord":"Anders Yronwood","region":"Dorne","title":"The Bloodroyal","heir":"Gwyneth Yronwood","overlord":"House Martell"},{"name":"House Allyrion","coatOfArms":" Gyronny Gules and Sable, a hand couped Or","words":" <i>No Foe May Pass</i>","seat":"Godsgrace","currentLord":"Delonne Allyrion","region":"Dorne","heir":"Ryon Allyrion","overlord":"House Martell"},{"name":"House Banefort","coatOfArms":" A black hooded man, on a grey field, within a fiery tressure<br>(<i>Cendrée, a hooded man sable within a tressure rayonné along the outer edge gules</i>)","seat":"Banefort","currentLord":"Quenten Banefort","region":"Westerlands","title":"<a href=\"#cite_note-Rasosappendix.7B.7B.7B3.7D.7D.7D-0\">[1]","overlord":"House Lannister","founder":"Hooded Man"},{"name":"House Bar Emmon","coatOfArms":" Fretty argent and white, a swordfish embowed haurient azure","seat":"Sharp Point","currentLord":"Duram Bar Emmon","region":"Massey's Hook","title":" Lord of Sharp Point","overlord":"House Baratheon of Dragonstone"},{"name":"House Beesbury","coatOfArms":" Paly or and sable, on a pale of the last three beehives of the first","words":" <i>Beware our Sting</i>","seat":"Honeyholt","currentLord":"Warryn Beesbury","region":"Reach","title":"Honeyholt","overlord":"House Hightower","founder":"Ellyn Ever Sweet"},{"name":"House Belmore","coatOfArms":" Six silver bells, 3, 2, 1, on a purple field<br>(<i>Purpure, six bells, 3, 2, 1, argent</i>)","seat":"Strongsong","currentLord":"Benedar Belmore","region":"The Vale","title":" Lord of Strongsong","overlord":"House Arryn"},{"name":"House Ambrose","coatOfArms":" Or, semy of ants gules","words":" <i>Never Resting</i>","currentLord":"Arthur Ambrose","region":"The Reach","overlord":"House Tyrell"},{"name":"House Blacktyde","coatOfArms":"<a href=\"#cite_note-CIT-0\">[1]","seat":"Blacktyde","region":"Iron Islands","title":"<a href=\"#cite_note-Racok24.7B.7B.7B3.7D.7D.7D-1\">[2]","overlord":"House Greyjoy"},{"name":"House Blackmont","coatOfArms":" A black vulture with a pink infant in its claws, on yellow","seat":"Blackmont","currentLord":"Larra Blackmont","region":"Dorne","heir":"Jynessa Blackmont","overlord":"House Martell"},{"name":"House Bracken","coatOfArms":" A red stallion upon a gold shield, on a brown field<br>(<i>Tenné, on an escutcheon or a stallion rampant gules</i>)","seat":"Stone Hedge","currentLord":"Jonos Bracken","region":"Riverlands","title":"Stone Hedge","overlord":"House Tully","founded":"Age of Heroes"},{"name":"House Botley","coatOfArms":" Vert, semy of fishes argent","seat":"Lordsport","currentLord":"Germund Botley","region":"Iron Islands","title":" Lord of Lordsport","overlord":"House Greyjoy"},{"name":"House Brax","coatOfArms":" A purple unicorn, on a silver field<br>(<i>Argent, a unicorn rampant purpure</i>)","seat":"Hornvale","currentLord":"Tytos Brax","region":"Westerlands","title":"Hornvale","heir":"Flement Brax","overlord":"House Lannister"},{"name":"House Blackwood","coatOfArms":" A flock of ravens surrounding a black shield charged with a dead weirwood, on a scarlet field<br>(<i>Gules, on an escutcheon sable a dead weirwood tree proper, all within an orle of ravens volant sable</i>)","seat":"Raventree Hall","currentLord":"Tytos Blackwood","region":"Riverlands","title":" Lord of Raventree","heir":"Brynden Blackwood","overlord":"House Baelish of Harrenhal","founded":"Age of Heroes"},{"name":"House Buckler","coatOfArms":" Three brass buckles, on a blue field<br>(<i>Azure, three buckles or</i>)","seat":"Bronzegate","currentLord":"Ralph Buckler","region":"the Stormlands","overlord":"House Baratheon"},{"name":"House Celtigar","coatOfArms":" Argent, semy of crabs gules","seat":"Claw Isle","currentLord":"Ardrian Celtigar","region":"Blackwater Bay","title":" Lord of Claw Isle","overlord":"House Baratheon of King's Landing","founded":" prior to ~112 years before the Conquest"},{"name":"House Bulwer","coatOfArms":" Sanguine, a bull`s skull argent","words":" <i>Death Before Disgrace</i>","seat":"Blackcrown","currentLord":"Alysanne Bulwer","region":"the Reach","overlord":"House Hightower","founder":" Bors the Breaker"},{"name":"House Caron","coatOfArms":" A field of black nightingales on yellow<br>(<i>Or, semé of nightingales sable</i>)","words":" <i>No Song so Sweet</i>","seat":"Nightsong","currentLord":"Rolland Storm","region":"Stormlands","title":"Lord of the Marches","overlord":"House Baratheon of Dragonstone"},{"name":"House Chester","coatOfArms":" A green hand on a gold escutcheon on a green field, a border of red rayonne","seat":"Greenshield","currentLord":"Moribald Chester","region":"the Reach","overlord":"House Tyrell"},{"name":"House Cerwyn","coatOfArms":" Argent, a battle-axe paleways sable","words":" <i>Honed and Ready</i>","seat":"Castle Cerwyn","currentLord":"Jonelle Cerwyn","region":"North","title":" Lord of Cerwyn","overlord":"House Bolton"},{"name":"House Coldwater","coatOfArms":" A blue pall with white borders, on a red field<br>(<i>Gules, a pall azure, fimbriated argent</i>)","seat":"Coldwater Burn","currentLord":"Royce Coldwater","region":"The Vale","title":" Lord of Coldwater Burn","overlord":"House Royce"},{"name":"House Chyttering","coatOfArms":" Three golden enhanced bendlets on a white shield<br>(<i>Argent, three bendlets enhanced or</i>)","seat":" Chyttering","currentLord":"Lucos Chyttering","region":"Crownlands","overlord":"House Baratheon of King's Landing"},{"name":"House Connington","coatOfArms":" Two combatant griffins, counterchanged, on a red and white field<br>(<i>Per pale gules and argent, two griffins combatant counterchanged</i>)","seat":"Griffin's Roost","currentLord":"Jon Connington","region":"The Stormlands","title":"Knight of Griffin's Roost","overlord":"House Baratheon"},{"name":"House Costayne","coatOfArms":" Quarterly; sable, a chalice argent; or, a rose sable","seat":"Three Towers","currentLord":"Tommen Costayne","region":"the Reach","overlord":"House Hightower"},{"name":"House Dalt","coatOfArms":" Purpure, semy of lemons Or","seat":"Lemonwood","currentLord":"Deziel Dalt","region":"Dorne","title":" The Knight of Lemonwood","heir":"Andrey Dalt","overlord":"House Martell"},{"name":"House Crakehall","coatOfArms":" A brindled boar on a brown field<br>(<i>Tenné, a boar brindled sable and argent</i>)","words":" <i>None so Fierce</i>","seat":"Crakehall","currentLord":"Roland Crakehall","region":"The Westerlands","title":"Crakehall","heir":"Tybolt Crakehall","overlord":"House Lannister","founder":"Crake the Boarkiller"},{"name":"House Dondarrion","coatOfArms":" A forked purple lightning bolt, on black field speckled with four-pointed stars<br>(<i>Sable, semé of mullets of four points argent, a lightning bolt forked purpure</i>)","seat":"Blackhaven","currentLord":"Beric Dondarrion","region":"the Stormlands","title":" Lord of Blackhaven","overlord":"House Baratheon","founded":"1 AC"},{"name":"House Cuy","coatOfArms":" Six yellow flowers on blue","seat":"Sunhouse","currentLord":"Branston Cuy","region":"Reach","overlord":"House Hightower","founded":"Andal Invasion"},{"name":"House Darry","coatOfArms":" A black plowman on a brown field<br>(<i>Tenné, a plowman sable</i>)","seat":"Darry","currentLord":"Mariya Darry","region":"Riverlands","overlord":"House Baelish of Harrenhal"},{"name":"House Drumm","coatOfArms":" Gules, a bone hand argent","currentLord":"Dunstan Drumm","region":"Iron Islands","title":" Lord of Old Wyk<br>The Drumm<br>The Bone Hand","overlord":"House Greyjoy","ancestralWeapon":"Red Rain"},{"name":"House Estermont","coatOfArms":" A dark-green sea-turtle on a pale-green field<br>(<i>Vert, a sea-turtle tergiant of the field</i>)","seat":"Greenstone","currentLord":"Eldon Estermont","region":"Stormlands","title":"Greenstone","heir":"Aemon Estermont","overlord":"House Baratheon of King's Landing"},{"name":"House Dustin","coatOfArms":" Two rusted longaxes with black shafts crossed, a black crown between their points, on yellow","seat":"Barrow Hall","currentLord":"Barbrey Dustin","region":"The North","title":"Barrowton","overlord":"House Bolton"},{"name":"House Errol","coatOfArms":" A yellow haystack, on an orange field<br>(<i>Tenné, a haystack or</i>)","seat":"Haystack Hall","currentLord":"Sebastion Errol","region":"the Stormlands","title":" Lord of Haystack Hall","overlord":"House Baratheon"},{"name":"House Estren","coatOfArms":" A green saltire between four red double-headed eagles, on a white field<br>(<i>Argent, a saltire vert between four double-headed eagles displayed gules</i>)","seat":"Wyndhall","currentLord":"Regenard Estren","region":"the Westerlands","title":" Lord of Wyndhall","overlord":"House Lannister"},{"name":"House Farman","coatOfArms":" Three silver ships on a blue field with a border of crimson and gold<br>(<i>Azure, three galleys argent within a bordure compony gules and or</i>)","seat":"Faircastle","currentLord":"Sebaston Farman","region":"Westerlands","title":" Lord of Fair Isle","overlord":"House Lannister"},{"name":"House Farwynd","seat":"Sealskin Point","currentLord":"Triston Farwynd","region":"Iron Islands","overlord":"House Greyjoy","cadetBranch":"House Farwynd of the Lonely Light"},{"name":"House Fell","coatOfArms":" Per fess, a white crescent moon on a black field above a green field, a sprucetree line between<br>(<i>Per fess sapinagé vert and sable, in dexter chief a moon increscent argent</i>)","seat":"Felwood","region":"the Stormlands","title":"Felwood","overlord":"House Baratheon"},{"name":"House Flint of Flint's Finger","coatOfArms":" Paly sable and cendrée on a pall inverted argent a hand couped of the second","seat":"Flint's Finger","currentLord":"Robin Flint","region":"The North","overlord":"House Bolton"},{"name":"House Flint of Widow's Watch","coatOfArms":" Azure, semy of whitecaps argent on a chief wavy Or two eyes of the second irised of the first and pupiled sable","words":" <i>Ever Vigilant</i>","seat":"Widow's Watch","currentLord":"Lyessa Flint","region":"The North","overlord":"House Bolton","cadetBranch":"House Flint of Flint's Finger"},{},{"name":"House Wyl","coatOfArms":" A black adder biting a heel on yellow","seat":"Wyl","region":"Dorne","overlord":"House Martell"},{"name":"House Flint of the mountains","seat":"northern mountains","currentLord":"Torghen Flint","region":"The North","title":" The Flint<br>Lord Flint","overlord":"House Stark","cadetBranch":"House Flint of Widow's Watch"},{"name":"House Lefford","coatOfArms":" A golden inverted pile on a sky-blue field, a yellow sun in the first<br>(<i>Bleu celeste, a pile reversed or, in canton a sun-in-splendor of the same</i>)","seat":"Golden Tooth","currentLord":"Alysanne Lefford","region":"Westerlands","overlord":"House Lannister","founded":"Andal invasion"},{},{"name":"House Reyne","coatOfArms":" A red lion rampant regardant with a forked tail, with gold teeth and claws, on a silver field<br>(<i>Argent, a lion rampant regardant queue-fourché gules, armed and langued or</i>)","seat":"Castamere","currentLord":" Extinct","region":"Westerlands","title":"Castamere","overlord":"House Lannister","cadetBranch":"House Vikary","died out":"261 AC"},{"name":"House Fossoway of Cider Hall","coatOfArms":" Or, an apple gules","words":" <i>Taste of Glory</i>","seat":"Cider Hall","region":"The Reach","title":"Cider Hall","overlord":"House Tyrell","cadetBranch":"House Fossoway of New Barrel","founder":"Foss the Archer"},{"name":"House Lothston","coatOfArms":" A black bat on a field per bend, silver and gold<br>(<i>Per bend argent and or, a bat displayed sable\")","seat":"Harrenhal","currentLord":" Extinct","region":"Riverlands","title":" Lord of Harrenhal","overlord":"House Tully","founder":"Lucas Lothston","founded":"151 AC","died out":"211 AC"},{"name":"House Fossoway of New Barrel","coatOfArms":" Or, an apple vert","seat":"New Barrel","currentLord":"Jon Fossoway","region":"The Reach","title":"Knight","overlord":"House Tyrell","founder":"Raymun Fossoway","founded":"209 AC"},{"name":"House Fowler","coatOfArms":" Argent, a hooded hawk trussed azure","words":" <i>Let Me Soar</i>","seat":"Skyreach","currentLord":"Franklyn Fowler","region":"Dorne","title":"Lord of Skyreach","overlord":"House Martell"},{"name":"House Goodbrook","coatOfArms":" A blue wavy bend, on a gold field<br>(<i>Or, a bend wavy azure</i>)","currentLord":"Lymond Goodbrook","region":"the Riverlands","overlord":"House Baelish of Harrenhal"},{"name":"House Goodbrother","coatOfArms":" Gules, a warhorn sable banded or.","seat":"Hammerhorn","currentLord":"Gorold Goodbrother","region":"Iron Islands","heir":"Greydon Goodbrother","overlord":"House Greyjoy","cadetBranch":"House Goodbrother of Downdelving"},{"name":"House Glover","coatOfArms":" Gules, a gauntlet argent","seat":"Deepwood Motte","currentLord":"Galbart Glover","region":"The North","title":"Deepwood Motte","heir":"Robett Glover","overlord":"House Stark"},{"name":"House Grafton","coatOfArms":" A yellow tower, burning, on a black pile, on a flame-red field<br>(<i>Gules, on a pile sable a tower or with flames issuant from the battlements proper</i>)","seat":"Gulltown","currentLord":"Gerold Grafton","region":"Vale of Arryn","title":"Gulltown","overlord":"House Arryn","founder":"Gerold Grafton"},{"name":"House Borrell","coatOfArms":" A white spider crab, on a grey-green field<br>(<i>Vert-cendrée, a spider crab argent</i>)","seat":"Breakwater","currentLord":"Godric Borrell","region":"Three Sisters","title":"Sweetsister","overlord":"House Sunderland"},{"name":"House Greenfield","coatOfArms":" A white double-tressure, on a green field<br>(<i>Vert, a double-tressure argent</i>)","seat":"Greenfield","currentLord":"Garth Greenfield","region":"Westerlands","title":"Knight","overlord":"House Lannister"},{"name":"House Grimm","coatOfArms":" An iron escutcheon with silver studs on a grey-green field strewn with longships proper","seat":"Grimston","currentLord":"Guthor Grimm","region":"The Reach","title":" Lord of Greyshield","overlord":"House Tyrell"},{"name":"House Tarbeck","coatOfArms":" A seven-pointed star, parts silver parts blue, on a silver and blue field<br>(<i>Gyronny argent and azure, a star of seven points counterchanged</i>)","seat":"Tarbeck Hall","currentLord":" Extinct","region":"Westerlands","title":"Tarbeck Hall","overlord":"House Lannister","died out":"261 AC"},{"name":"House Harlaw","coatOfArms":" Sable, a scythe argent","seat":"Ten Towers","currentLord":"Rodrik Harlaw","region":"Iron Islands","title":" Lord of Harlaw","heir":"Harras Harlaw","overlord":"House Greyjoy","cadetBranch":"House Harlaw of Grey Garden"},{"name":"House Hunter","coatOfArms":" Five silver arrows, fanned, on a brown field<br>(<i>Tenné, a sheaf of five arrows, points to chief, argent</i>)","seat":"Longbow Hall","currentLord":"Gilwood Hunter","region":"The Vale","title":"Longbow Hall","heir":"Eustace Hunter","overlord":"House Arryn"},{"name":"House Jast","coatOfArms":" An inverted yellow pall between three yellow lions' heads, on a black field<br>(<i>Sable, a pall reversed between three lions' heads erased or</i>)","currentLord":"Antario Jast","region":"the Westerlands","overlord":"House Lannister"},{"name":"House Hetherspoon","coatOfArms":" An oak spoon within a white cartouche, on a field of orange and black diamonds<br>(<i>Lozengy tenné and sable, on a cartouche argent a spoon or</i>)","currentLord":"Tybolt Hetherspoon","region":"The Westerlands","title":" Ser","overlord":"House Lannister"},{"name":"House Hewett","coatOfArms":" an oaken escutcheon studded with iron on a field bendy of undulating blue and white","seat":"Lord Hewett's castle","currentLord":"Humfrey Hewett","region":"The Reach","title":" Lord of Oakenshield","overlord":"House Tyrell"},{"name":"House Jordayne","coatOfArms":" Chequy light and dark green, a quill or.","words":" <i>Let it be Written</i>","seat":"The Tor","currentLord":"Trebor Jordayne","region":"Dorne","title":" Lord of the Tor","heir":"Myria Jordayne","overlord":"House Martell"},{"name":"House Liddle","coatOfArms":" Per pale argent and vert, a fir tree line between, three brown pinecones on the argent","currentLord":"Torren Liddle","region":"The North","title":" The Liddle<br>Lord Liddle","overlord":"House Stark"},{"name":"House Vaith","coatOfArms":" Tenny, on a pile Or three leopards statant sable","seat":"Vaith","currentLord":"Daeron Vaith","region":"Dorne","title":"Lord of the Red Dunes","overlord":"House Martell","founded":"Andal Invasion"},{"name":"House Karstark","coatOfArms":" Sable, a sunburst argent","words":" <i>The Sun of Winter</i>","seat":"Karhold","currentLord":"Harrion Karstark","region":"The North","title":"Karhold","heir":"Alys Karstark","overlord":"House Bolton","founder":"Karlon Stark","founded":" One thousand years ago"},{"name":"House Lydden","coatOfArms":" A white badger on a per pale green and brown field<br>(<i>Per pale vert and tenné, a badger passant argent</i>)","seat":"Deep Den","currentLord":"Lewys Lydden","region":"the Westerlands","title":" Lord of the Deep Den","overlord":"House Lannister"},{"name":"House Lynderly","coatOfArms":" A black field strewn with green vipers<br>(<i>Sable, semé of snakes vert</i>)","seat":"Snakewood","currentLord":"Jon Lynderly","region":"The Vale","title":"the Snakewood","heir":"Terrance Lynderly","overlord":"House Arryn"},{"name":"House Locke","coatOfArms":" Two bronze keys crossed on an argent pale on purpure.","seat":"Oldcastle","currentLord":"Ondrew Locke","region":"the North","title":" Lord of Oldcastle","overlord":"House Bolton"},{"name":"House Greyiron","coatOfArms":" The sea king's head, white with dark green seaweed beard and hair, a black crown on a grey field","seat":"Orkmont","region":"Iron Islands","title":"King of the Iron Islands","overlord":" Extinct"},{"name":"House Gardener","coatOfArms":" Argent, a hand couped vert","seat":"Highgarden","currentLord":" Extinct","region":"Reach","title":"King of the Reach","founder":"Garth the Gardener","founded":"Age of Heroes","died out":"1 AC"},{"name":"House Casterly","seat":"Casterly Rock","currentLord":" Extinct","region":"Westerlands","title":" Lord of Casterly Rock","cadetBranch":"House Lannister","founder":"Corlos","founded":"Age of Heroes"},{"name":"House Darklyn","coatOfArms":" Fusily sable and or, upon a pale in dexter gules seven escutcheons argent","seat":"Dun Fort","currentLord":" Extinct","region":"Crownlands","title":"Duskendale","overlord":"House Targaryen","cadetBranch":"House Darke","founded":"Age of Heroes","died out":"277 AC"},{"name":"House Hoare","coatOfArms":" Per saltire, two heavy silver chains crossing between a gold longship on a black field, a dark green pine on a white field, a cluster of red grapes on a gold field, and a black raven flying in a blue sky<br>(<i>Per saltire sable, azure, argent and or, two chains throughout saltirewise argent between in chief a longship or, in dexter a raven volant sable, in sinister a pine-tree vert and in base a bunch of grapes gules</i>)","seat":"Orkmont","region":"Iron Islands","title":"King of the Iron Islands","died out":"2 BC"},{"name":"House Buckwell","coatOfArms":" A rack of golden antlers, on a field of vair<br>(<i>Vair, a stag's attire or</i>)","words":" <i>Pride and Purpose</i>","seat":"the Antlers","region":"Crownlands","title":" Lord of the Antlers","overlord":"House Baratheon of King's Landing"},{"name":"House Blackfyre","coatOfArms":" Gules, a three headed dragon breathing flames sable","currentLord":" Extinct","overlord":"House Targaryen","ancestralWeapon":"Blackfyre","founder":"Daemon Blackfyre","founded":"184 AC","died out":"260 AC"},{},{},{"name":"House Hayford","coatOfArms":" Green fretty over gold, a green pale wavy","seat":"Hayford","currentLord":"Ermesande Hayford","region":"Crownlands","title":" Lord of Hayford","overlord":"House Baratheon of King's Landing"},{"name":"House Moore","coatOfArms":" Three bronze spearheads, on a white field, within a bronze embattled border<br>(<i>Argent, three spearheads within a bordure embattled tenné</i>)","region":"The Vale","overlord":"House Arryn"},{"name":"House Codd","words":" <i>Though All Men Do Despise Us</i>","region":"Iron Islands","overlord":"House Greyjoy"},{"name":"House Humble","region":"Iron Islands","overlord":"House Greyjoy"},{"name":"House Stonetree","coatOfArms":" A bare stone tree, grey on black","region":"Iron Islands","overlord":"House Harlaw"},{"name":"House Cassel","coatOfArms":" Ten white wolf heads, 4-3-2-1, on grey with a black border","currentLord":"Beth Cassel","region":"The North","overlord":"House Stark"},{"name":"House Knott","coatOfArms":" Argent, a saltire surmounted by a fret tenny","region":"the North","title":" The Knott","overlord":"House Bolton"},{"name":"House Harclay","coatOfArms":" Azure, on a bend argent a hurt between an increscent and decrescent of the first","region":"North","title":" Lord Harclay<br>The Harclay","overlord":"House Bolton"},{"name":"House Marsh","coatOfArms":" Or, ten frogs vert","region":"The North","overlord":"House Bolton"},{"name":"House Trant","coatOfArms":" A black hanged man, on a blue field<br>(<i>Azure, a hanged man sable</i>)","words":" <i>So End Our Foes</i>","seat":"Gallowsgrey","region":"Stormlands","title":" Lord of Gallowsgrey","overlord":"House Baratheon"},{"name":"House Selmy","coatOfArms":" Three stalks of yellow wheat, on a brown field<br>(<i>Tenné, three stalks of wheat or</i>)","seat":"Harvest Hall","currentLord":"Arstan Selmy","region":"Stormlands","title":"Harvest Hall","overlord":"House Baratheon"},{"name":"House Mudd","coatOfArms":" A golden crown studded with emeralds, on a red-brown field<br>(<i>Tenné, an ancient crown or studded with emeralds vert</i>)","seat":"Oldstones","region":"Riverlands","title":"King of the Rivers and the Hills"},{"name":"House Fisher","coatOfArms":" A crowned catfish, spotted grey, on a blue field<br>(<i>Azure, a catfish cendrée, crowned or</i>)","seat":"Misty Isle","currentLord":" Extinct","region":"Riverlands","title":"River king"},{"name":"House Merlyn","coatOfArms":" Argent, Twining waterspouts vert","seat":"Pebbleton","region":"Iron Islands","overlord":"House Greyjoy"},{"name":"House Ferren","coatOfArms":" Per saltire, checkered red and gold, a silver and black ferret on a green field<br>(<i>Per saltire chequy gules and or and vert, in each flank point a ferret argent and sable</i>)","region":"the Westerlands","overlord":"House Lannister"},{"name":"House Slynt","coatOfArms":" A bloody gold spear, on a black field, within a checkered gold and black border<br>(<i>Sable, a spear or, tipped gules, within a bordure chequy of the field and of the second</i>)","seat":"Harrenhal","currentLord":"Morros Slynt","region":" None","heir":"Jothos Slynt","overlord":"House Baratheon of King's Landing","founder":"Janos Slynt","founded":"298 AC"},{"name":"House Ryger","coatOfArms":" A green weeping willow, on a white field<br>(<i>Argent, a willow-tree vert</i>)","seat":"Willow Wood","region":"the Riverlands","overlord":"House Baelish of Harrenhal"},{"name":"House Broom","coatOfArms":" A silver helm crested with a sprig of broom, on a checkered black and green field<br>(<i>Chequy sable and vert, a helm argent, crested with a sprig of broom proper</i>)","region":"the Westerlands","overlord":"House Lannister"},{"name":"House Serrett","coatOfArms":" A peacock in his pride, on a cream field<br>(<i>Argent, a peacock-in-his-pride proper</i>)","words":" <i>I Have No Rival</i>","seat":"Silverhill","region":"the Westerlands","overlord":"House Lannister"},{"name":"House Hersy","coatOfArms":" A white winged chalice, on a pink field<br>(<i>Carnation, a winged cup displayed argent</i>)","seat":"Newkeep","region":"the Vale","overlord":"House Arryn"},{"name":"House Baelish","coatOfArms":" A grey stone head with fiery eyes, on a light green field<br>(<i>Vert, a stone head cendrée, orbed gules</i>)","seat":"unnamed tower","currentLord":"Petyr Baelish","region":"the Vale","overlord":"House Arryn","cadetBranch":"House Baelish of Harrenhal","founder":"A Braavosi sellsword"},{"name":"House Egen","coatOfArms":" A yellow sun, white crescent moon, and silver star on a blue chief, above a white field<br>(<i>Argent, on a chief azure a moon increscent of the first between a sun-in-splendour or and a mullet of the first</i>)","words":" <i>By Day or Night</i>","region":"the Vale","overlord":"House Arryn"},{"name":"House Melcolm","coatOfArms":" A rusty anchor, on a turquoise field, beneath yellow chief with three blue plates<br>(<i>Azure, an anchor tenné, on a chief or three hurts</i>)","seat":"Old Anchor","region":"the Vale","overlord":"House Arryn"},{"name":"House Seaworth","coatOfArms":" A black ship on a pale grey field, with a white onion on its sails<br>(<i>Cendrée, a ship sable, its sail charged with an onion argent</i>)","currentLord":"Davos Seaworth","region":"the Stormlands","heir":"Devan Seaworth","overlord":"House Baratheon of Dragonstone","founder":"Davos Seaworth","founded":"284 AC"},{"name":"House Crane","coatOfArms":" Azure, cranes in chevron or","seat":"Red Lake","region":"Reach","overlord":"House Tyrell","founder":"Rose of Red Lake"},{"name":"House Webber","coatOfArms":" Sable, a cobweb argent thereon a spider gules","seat":"Coldmoat","region":"the Reach","title":" Lord of Coldmoat","overlord":"House Rowan"},{"name":"House Greystark","seat":"Wolf's Den","currentLord":" Extinct","region":"the North","overlord":"House Stark"},{"name":"House Osgrey","coatOfArms":" Argent, a lion rampant chequy vert and or","seat":"Standfast","region":"the Reach","title":"Marshall of the Northmarch","overlord":"House Rowan","cadetBranch":"Osgrey of Leafy Lake"},{"name":"House Osgrey of Leafy Lake","seat":"Leafy Lake","currentLord":" Extinct","region":"the Reach","overlord":"House Osgrey","died out":"210 AC"},{"name":"House Butterwell","coatOfArms":" Barry wavy green, white, and yellow<br>(<i>Barry wavy vert, argent, and or</i>)","seat":"Whitewalls","region":"the Riverlands","overlord":"House Baelish of Harrenhal"},{"name":"House Caswell","coatOfArms":" Argent, a centaur with bow or","seat":"Bitterbridge","currentLord":"Lorent Caswell","region":"The Reach","title":"Bitterbridge","overlord":"House Tyrell"},{"name":"House Leygood","coatOfArms":" Tenny, three thunderbolts in fess sable","region":"Reach","overlord":"House Tyrell"},{"name":"House Durwell","region":"the Reach","overlord":"House Tyrell"},{"name":"House Conklyn","region":"the Reach","overlord":"House Tyrell"},{"name":"House Stackhouse","region":"the Reach","overlord":"House Tyrell"},{"name":"House Payne","coatOfArms":" Gold coins in the checks of a checkered purple and white field<br>(<i>Chequy purpure and argent, each chequer charged with a bezant</i>)","region":"the Westerlands","overlord":"House Lannister"},{"name":"House Wylde","coatOfArms":" A blue-green maelstrom, on a gold field<br>(<i>Or, a maelstrom azure</i>)","seat":"Rain House","currentLord":"Casper Wylde","region":"Stormlands","title":"Rain House","overlord":"House Baratheon"},{"name":"House Inchfield","coatOfArms":" Cendrée, a bend sinister chequy sable and argent","region":"the Reach","overlord":"House Tyrell"},{"name":"House Vyrwel","coatOfArms":" a silver wyvern within a red double tressure on sable","seat":"Darkdell","region":"the Reach","overlord":"House Tyrell"},{"name":"House Uffering","coatOfArms":" Paly tenné and cendrée, upon a chief argent seven hands couped vert","region":"the Reach","overlord":"House Tyrell"},{"name":"House Poole","coatOfArms":" White, a roundel azure, a tressure cendrée","region":"the North","overlord":"House Bolton"},{"name":"House Rambton","coatOfArms":" Gules, a ram's head cabossed argent attired or","region":"Crownlands","overlord":"House Sunglass"},{"name":"House Myatt","coatOfArms":" A spotted yellow-and-black treecat, on a mud-brown field<br>(<i>Tenné, a treecat or pelleté</i>)","region":"Westerlands","overlord":"House Lannister"},{"name":"House Staunton","coatOfArms":" two black wings upon a white fess on checkered black and grey","seat":"Rook's Rest","region":"Crownlands","overlord":"House Baratheon of Dragonstone"},{"name":"House Farring","coatOfArms":" Per pale purpure and argent, two knights combatant crossing swords counterchanged","region":"Crownlands","overlord":"House Baratheon of Dragonstone"},{"name":"House Lorch","coatOfArms":" A black manticore on a white field, beneath a crimson chief with three gold coins<br>(<i>Argent, a manticore passant sable, on a chief gules three bezants</i>)","currentLord":"Lorent Lorch","region":"the Westerlands","overlord":"House Lannister"},{"name":"House Bywater","coatOfArms":" Blue frets on a white field, three silver fish on a blue chief<br>(<i>Argent fretty azure, on a chief of the second three fish of the field</i>)","region":"Crownlands","overlord":"House Baratheon of King's Landing"},{"name":"House Thorne","coatOfArms":" Gules, a flail argent within an bordure rayonne sable","region":"Crownlands","overlord":"House Baratheon of King's Landing"},{"name":"House Varner","coatOfArms":" Ermines, a weasel argent","currentLord":"Steffon Varner","region":"the Reach","overlord":"House Tyrell"},{"name":"House Mollen","coatOfArms":" White, upon a pile vert a snowy pine tree proper","region":"the North","overlord":"House Stark"},{"name":"House Willum","coatOfArms":" three silver longswords crossed on black beneath a dragonbone skeleton on a white chief","region":"the Reach","overlord":"House Tyrell"},{"name":"House Shermer","coatOfArms":" a field of copper nails on blue, a copper border rayonne","seat":"Smithyton","region":"the Reach","overlord":"House Tyrell"},{"name":"House Blackbar","coatOfArms":" Argent, a fess sable","seat":"Bandallon","region":"the Reach","title":" Lord of Bandallon","overlord":"House Tyrell"},{},{"name":"House Dunn","coatOfArms":" per pale black and pink, a countercharged two-headed pelican","region":"the Reach","overlord":"House Tyrell"},{"name":"House Rykker","coatOfArms":" Azure, a cross saltire argent charged with two crossed warhammers sable","seat":"Dun Fort","currentLord":"Renfred Rykker","region":"Crownlands","title":"Duskendale","overlord":"House Baratheon of King's Landing"},{"name":"House Footly","coatOfArms":" a field of silver caltrops on black","words":" <i>Tread Lightly Here</i>","seat":"Tumbleton","region":"the Reach","overlord":"House Tyrell"},{"name":"House Wythers","coatOfArms":" a grey squirrel on white with red border","region":"the Reach","overlord":"House Tyrell"},{"name":"House Falwell","coatOfArms":" A fool in red and gold motley juggling five suns, on a black field<br>(<i>Sable, a fool proper clothed in motley gules and or, juggling five suns-in-splendour of the last</i>)","region":"the Westerlands","overlord":"House Lannister"},{"name":"House Smallwood","coatOfArms":" Six brown acorns, on a yellow field<br>(<i>Or, six acorns, 3, 2, 1, tenné</i>)","words":" <i>From These Beginnings</i>","seat":"Acorn Hall","currentLord":"Theomar Smallwood","region":"The Riverlands","title":"Acorn Hall","overlord":"House Vance of Wayfarer's Rest"},{"name":"House Bettley","coatOfArms":" Three blue beetles, on a gold field<br>(<i>Or, three beetles azure</i>)","region":"the Westerlands","overlord":"House Lannister"},{"name":"House Kenning of Kayce","coatOfArms":" Four sunbursts counterchanged on a quartered orange and black field<br>(<i>Quarterly tenné and sable, four suns-in-splendour counterchanged</i>)","seat":"Kayce","currentLord":"Terrence Kenning","region":"Westerlands","title":" Lord of Kayce","overlord":"House Lannister","founder":"Herrock Kenning"},{"name":"House Peckledon","coatOfArms":" Ten purple stars, on a yellow field<br>(<i>Or, ten mullets, 4, 3, 2, 1, purpure</i>)","words":" <i>Unflinching</i>","region":"the Westerlands","overlord":"House Lannister"},{"name":"House Foote","coatOfArms":" A copper dagger across a black chevron, on a white field<br>(<i>Argent, a chevron reversed sable, surmounted by a dagger erect tenné</i>)","region":"the Westerlands","overlord":"House Lannister","cadetBranch":"House Foote of Nightsong"},{"name":"House Sarsfield","coatOfArms":" A green arrow on a white bend, on a green field<br>(<i>Vert, on a bend argent an arrow of the field, point to dexter chief</i>)","words":" <i>True to the Mark</i>","seat":"Sarsfield","region":"the Westerlands","overlord":"House Lannister"},{"name":"House Grell","coatOfArms":" Three red martlets on a white bend, on a blue field<br>(<i>Azure, on a bend argent three martlets gules</i>)","region":"the Riverlands","overlord":"House Tully"},{"name":"House Wayn","coatOfArms":" Four wheels counterchanged on a quartered blue and white field<br>(<i>Quarterly azure and argent, four wheels counterchanged</i>)","region":"the Riverlands","overlord":"House Tully"},{"name":"House Meadows","coatOfArms":" a border of flowers of many colors and varieties on green","seat":"Grassfield Keep","currentLord":"Elwood Meadows","region":"Reach","title":"Grassy Vale","overlord":"House Baratheon of Dragonstone"},{"name":"House Kettleblack","coatOfArms":" Gules, a kettle within an orle sable","region":"Crownlands","overlord":"House Baratheon of King's Landing"},{"name":"House Blount","coatOfArms":" A red bend sinister between two black porcupines, on a green field<br>(<i>Vert, a bend sinister gules between two porcupines sable</i>)","region":"Crownlands","overlord":"House Baratheon of King's Landing"},{"name":"House Vance of Wayfarer's Rest","coatOfArms":" Quartered, a black dragon on a white field and two golden eyes in a golden ring on a black field<br>(<i>Quarterly, first and fourth, argent, a dragon sable, second and third, sable, a pair of eyes within an annulet or</i>)","seat":"Wayfarer's Rest","currentLord":"Karyl Vance","region":"Riverlands","overlord":"House Baelish of Harrenhal","founder":"Armistead Vance"},{"name":"House Yarwyck","coatOfArms":" Two bronze halberds crossed between four red diamonds, on a white field<br>(<i>Argent, two halberds saltirewise tenné, hafted sable, between four lozenges gules</i>)","region":"Westerlands","overlord":"House Lannister"},{"name":"House Mallery","coatOfArms":" Purpure, six mullets argent","region":"Crownlands","overlord":"House Baratheon of King's Landing"},{"name":"House Erenford","coatOfArms":" A golden heron, beak and legs black, standing with a silver fish in its beak, on a pink field<br>(<i>Carnation, a heron or, beaked and membered sable, clasped in its mouth a fish argent</i>)","region":"Riverlands","overlord":"House Frey"},{"name":"House Hollard","coatOfArms":" Barry gules and carnation, a chief azure with three crowns Or","currentLord":" Extinct","region":"Crownlands","overlord":"House Darklyn","died out":"300 AC"},{"name":"House Goodbrother of Downdelving","seat":"Downdelving","region":"Iron Islands","overlord":"House Goodbrother"},{"name":"House Goodbrother of Crow Spike Keep","seat":"Crow Spike Keep","region":"Iron Islands","overlord":"House Goodbrother"},{"name":"House Haigh","coatOfArms":" A black pitchfork on a gold bend sinister, on a russet field<br>(<i>Tenné, on a bend sinister or a pitchfork sable</i>)","region":"Riverlands","overlord":"House Frey"},{"name":"House Goodbrother of Corpse Lake","seat":"Corpse Lake","region":"Iron Islands","overlord":"House Goodbrother"},{"name":"House Foote of Nightsong","seat":"Nightsong","currentLord":"Philip Foote","region":"Stormlands","title":"Nightsong","overlord":"House Baratheon of King's Landing","founder":"Philip Foote","founded":"299 AC"},{"name":"House Baelish of Harrenhal","coatOfArms":" A field of silver mockingbirds, on a green field<br>(<i>Vert, semé of mockingbirds argent</i>)","seat":"Harrenhal","currentLord":"Petyr Baelish","region":"Riverlands","title":"Lord Paramount of the Trident","overlord":"House Baratheon of King's Landing","founder":"Petyr Baelish","founded":"299 AC"},{"name":"House Norcross","coatOfArms":" Argent, a cross embattled sable","region":"the Reach","overlord":"House Tyrell"},{"name":"House Bolling","coatOfArms":" Vairy orange and blue, upon a black canton, a golden stag beneath an orange bend sinister<br>(<i>Vairy tenné and azure, on a canton sable a stag or debruised by a bend sinister of the first</i>)","region":"the Stormlands","overlord":"House Baratheon"},{"name":"House Hardyng","coatOfArms":" A field of red and white diamonds<br>(<i>Lozengy argent and gules</i>)","region":"The Vale","overlord":"House Waynwood"},{"name":"House Hawick","coatOfArms":" White seabirds strewn across a blue field<br>(<i>Azure, semé of seabirds argent</i>)","seat":"Saltpans","region":"the Riverlands","overlord":"House Baelish of Harrenhal"},{"name":"House Hasty","coatOfArms":" A white bend cotised, on a purple field<br>(<i>Purpure, a bend cotised argent</i>)","region":"the Stormlands","overlord":"House Baratheon"},{"name":"House Cockshaw","coatOfArms":" Sable, three feathers in fess gules argent and or","region":"the Reach","overlord":"House Tyrell"},{"name":"House Vypren","coatOfArms":" A black toad on white lily pad, on a green field<br>(<i>Vert, a toad sable atop a lilypad argent</i>)","currentLord":"Lucias Vypren","heir":"Damon Vypren","overlord":"House Baelish of Harrenhal"},{"name":"House Blanetree","coatOfArms":" Green and brown maple leaves, strewn across a yellow field<br>(<i>Or, semé of maple leaves vert and tenné</i>)","region":"Riverlands","overlord":"House Tully"},{"name":"House Ashford","coatOfArms":" Tenny, a sun in splendour beneath a chevron inverted argent","words":" <i>Our Sun Shines Bright</i>","seat":"Ashford","region":"Reach","title":"Ashford","overlord":"House Tyrell"},{"name":"House Peake","coatOfArms":" Tenny, three castles sable","seat":"Starpike","currentLord":"Titus Peake","region":"Reach","title":"Starpike","overlord":"House Tyrell"},{"name":"House Ball","coatOfArms":" Three white plates upon a chevron red on a white field","region":"The Reach","overlord":"House Tyrell"},{"name":"House Rhysling","coatOfArms":" An oaken door banded with iron, in a grey stone doorway, on black masonry","region":"the Reach","overlord":"House Tyrell"},{"name":"Henly (House Ashford)","allegiance":"House Ashford","book(s)":"The Hedge Knight"},{"name":"House Shawney","coatOfArms":" Per fesse, a divided blue, red, green field above, a white catfish on a black field below<br>(<i>Per fesse, the first tierced in pale azure, gules and vert, the second sable, a catfish argent</i>)","region":"Riverlands","overlord":"House Tully"},{"name":"House Lonmouth","coatOfArms":" Quartered of six: red lips strewn on a yellow field, yellow skulls strewn on a black field<br>(<i>Quarterly of six, first, third and fifth, or, semé of lips gules, second, fourth and sixth, sable, semé of skulls of the first</i>)","words":" <i>The Choice is Yours</i>","region":"the Stormlands","overlord":"House Baratheon"},{"name":"House Chelsted","coatOfArms":" Per bend green and white shield, a spiked mace and a silver dagger crossed<br>(<i>Per bend vert and argent, in pale a mace surmounted by a dagger in fesse of the second</i>)","region":"Crownlands","overlord":"House Baratheon of King's Landing"},{"name":"House Byrch","coatOfArms":" Gryonny white and black quartered with a silver axe on a green field<br>(<i>Quarterly, first and fourth, gyronny argent and sable, second and third, vert, an axe palewise argent</i>)","region":"Crownlands","overlord":"House Baratheon of King's Landing"},{"name":"House Turnberry","coatOfArms":" Nine strawberries on a white saltire, on a field of green and red vairy in point<br>(<i>Vairy-in-point vert and gules, on a saltire argent nine strawberries of the second</i>)","region":"the Westerlands","overlord":"House Lannister"},{"name":"House Spicer","coatOfArms":" Three black pepperpots on a saffron bend, across a field of green and silver stripes <br>(<i>Paly vert and argent, three pepperpots sable on a bend tenné</i>)","seat":"Castamere","currentLord":"Rolph Spicer","region":"Westerlands","title":"Lord of Castamere","heir":"Sybell Spicer","overlord":"House Lannister"},{"name":"House Graceford","coatOfArms":" Tenny, on a pale wavy argent the Mother's face proper","words":" <i>Work Her Will</i>","seat":"Holyhall","currentLord":"Alyce Graceford","region":"Reach","overlord":"House Tyrell"},{"name":"House Grandison","coatOfArms":" A black sleeping lion, on a yellow field<br>(<i>Or, a lion dormant sable</i>)","words":" <i>Rouse Me Not</i>","seat":"Grandview","currentLord":"Hugh Grandison","region":"Stormlands","title":" Lord of Grandview","overlord":"House Baratheon"},{},{"name":"House Toyne","coatOfArms":" A black winged heart, on a gold field, within a black embattled border<br><i>Or, a winged heart within a bordure embattled sable</i>)","words":" <i>Fly High, Fly Far</i>","region":"Stormlands","overlord":"House Baratheon","died out":"281 AC"},{"name":"House Lychester","coatOfArms":" A black talon, on an orange and white gyronny field<br>(<i>Gyronny tenné and argent, an eagle's leg erased sable</i>)","seat":"Castle Lychester","currentLord":"Lymond Lychester","region":"Riverlands","overlord":"House Baelish of Harrenhal"},{"name":"House Charlton","coatOfArms":" Three sprigs of mistletoe, green and red, on a gold field within a green border<br>(<i>Or, three sprigs of mistletoe vert, fructed gules, within a bordure of the second</i>)","region":"Riverlands","overlord":"House Frey"},{"name":"House Roote","coatOfArms":" A brown double-headed horse on a field of wavy green and green<br>(<i>Wavy vert and vert, a two-headed horse tenné</i>)","seat":"Lord Harroway's Town","region":"Riverlands","overlord":"House Baelish of Harrenhal"},{"name":"House Deddings","region":"the Riverlands","overlord":"House Baelish of Harrenhal"},{"name":"House Risley","coatOfArms":" A black knight on a black rearing horse on white, bearing a golden lance and a white shield, upon which is seen the above in miniature","region":"Reach","overlord":"House Tyrell"},{"name":"House Nayland","seat":"Hag's Mire","region":"Riverlands","overlord":"House Frey"},{"name":"House Boggs","region":"Crownlands","overlord":"House Baratheon of King's Landing"},{"name":"House Massey","coatOfArms":" A triple spiral; red, green and blue, on white","seat":"Stonedance","region":"Crownlands","title":"Stonedance","overlord":"House Baratheon of King's Landing","founder":"Maldon Massey","founded":"Age of Heroes"},{"name":"House Cafferen","coatOfArms":" Two white fawns counter salient, on a green field<br>(<i>Vert, two fawns counter-salient argent</i>)","seat":"Fawnton","region":"the Stormlands","overlord":"House Baratheon"},{"name":"House Stout","coatOfArms":" Chevronny tenné and Or","seat":"Goldgrass","currentLord":"Harwood Stout","region":"The North","title":"Goldgrass","overlord":"House Dustin"},{"name":"House Follard","coatOfArms":" Gyronny gules and argent, on a canton Or a fool's cap two peaked of the first and second","words":" <i>None so Wise</i>","region":"Crownlands","overlord":"House Baratheon of King's Landing"},{"name":"House Harte","coatOfArms":" Three red hart's heads caboshed on a white bend on vair","region":"Crownlands","overlord":"House Baratheon of King's Landing"},{"name":"House Harroway","coatOfArms":" Per bend sinister orange and sable rayonné, a castle counterchanged<br>(<i>Per bend sinister rayonné tenné and sable, a castle counterchanged</i>)","seat":"Harrenhal","currentLord":" Extinct","region":"Riverlands","title":"Harrenhal","overlord":"House Tully","died out":"44 AC"},{"name":"House Magnar","coatOfArms":" Argent, a lobster vert holding a harpoon sable","seat":"Kingshouse","region":"the North","overlord":"House Bolton"},{"name":"House Gower","coatOfArms":" Nine yellow trefoils on a black cross, on an ermine field<br>(<i>Ermine, on a cross sable nine trefoils or</i>)","region":"the Stormlands","overlord":"House Baratheon"},{"name":"House Woodfoot","seat":"Bear Island","currentLord":" Extinct","region":"the North","overlord":"House Stark"},{"name":"House Frey of Riverrun","seat":"Riverrun","currentLord":"Emmon Frey","region":"Riverlands","title":"Riverrun","heir":"Tywin Frey","overlord":"House Baelish of Harrenhal","founder":"Emmon Frey","founded":"299 AC"},{"name":"House Brune of Brownhollow","coatOfArms":" Argent, a bear's paw erased within a double tressure tenné","seat":"Brownhollow","currentLord":"Bennard Brune","region":"Crownlands","title":"Knight","overlord":"House Baratheon of King's Landing"},{"name":"House Gaunt","coatOfArms":" Purpure, three lances palewise in fess between two flaunches sable","region":"Crownlands","overlord":"House Baratheon of King's Landing"},{"name":"House Wensington","coatOfArms":" Two golden trumpets crossed on a blue field, beneath a gold chief with three black stags<br>(<i>Azure, two trumpets saltirewise or, on a chief of the second three stags salient sable</i>)","words":" <i>Sound The Charge</i>","region":"Stormlands","overlord":"House Baratheon"},{"name":"House Brune of the Dyre Den","seat":"Dyre Den","currentLord":"Eustace Brune","region":"Crownlands","title":"Dyre Den","overlord":"House Baratheon of King's Landing","cadetBranch":"House Brune of Brownhollow"},{"name":"House Cave","region":"Crownlands","overlord":"House Baratheon of King's Landing"},{"name":"House Crabb","seat":"Whispers","region":"Crownlands","overlord":"House Baratheon of King's Landing"},{"name":"House Cressey","coatOfArms":" Seven silver coins on a red bend sinister, between two silver helmets, on a blue field<br>(<i>Azure, on a bend sinister gules seven plates, between two helmets argent</i>)","region":"Crownlands","overlord":"House Baratheon of King's Landing"},{"name":"House Hardy","region":"Crownlands","overlord":"House Baratheon of King's Landing"},{"name":"House Edgerton","coatOfArms":" Purpure, a wheel flaming tenny quartered with half-fusilly sable and argent","region":"Crownlands","overlord":"House Baratheon of King's Landing"},{"name":"House Hogg","seat":"Sow's Horn","currentLord":"Roger Hogg","region":"Crownlands","title":" the Knight of Sow's Horn","overlord":"House Hayford"},{"name":"House Langward","coatOfArms":" Per fess undy: A crown of white stars on burgundy above black","region":"Crownlands","overlord":"House Baratheon of King's Landing"},{"name":"House Pyle","coatOfArms":" A grey iron greathelm on white","region":"Crownlands","overlord":"House Baratheon of King's Landing"},{"name":"House Pyne","region":"Crownlands","overlord":"House Baratheon of King's Landing"},{"name":"House Wendwater","coatOfArms":" A green engrailed pall, inverted on white, dividing three trees, green, red and bare","words":" <i>For All Seasons</i>","region":"Crownlands","overlord":"House Baratheon of King's Landing"},{"name":"House Manning","coatOfArms":" A red sea lion between two black pallets on white","region":"Crownlands","overlord":"House Baratheon of King's Landing"},{"name":"House Rollingford","coatOfArms":" Six roundels fountain, 3-2-1, on grey","region":"Crownlands","overlord":"House Baratheon of King's Landing"},{"name":"House Condon","coatOfArms":" An eagle's head between crossed tridents, red on white","region":"North","overlord":"House Cerwyn"},{"name":"House Ironsmith","coatOfArms":" Or, a sword palewise between four horseshoes sable all within a bordure vert","region":"North","overlord":"House Bolton"},{"name":"House Lightfoot","coatOfArms":" Tenny, a trail of footprints in bend sinister argent","region":"North","overlord":"House Bolton"},{"name":"House Moss","coatOfArms":" A bend orange on vairy grey and green","region":"North","overlord":"House Bolton"},{"name":"House Fenn","coatOfArms":" Purpure, three water lilies sable","region":"The Neck","overlord":"House Reed"},{"name":"House Lake (north)","coatOfArms":" Tenny, seven pommes arranged 2-2-2-1","region":"North","overlord":"House Bolton"},{"name":"House Overton","coatOfArms":" Sable, a fess chequy argent and Or","region":"North","overlord":"House Bolton"},{"name":"House Waterman","coatOfArms":" Argent, two oars saltirewise tenny between as many flaunces azure","region":"North","overlord":"House Bolton"},{"name":"House Slate","coatOfArms":" Pale grey, a double tressure white","seat":"Blackpool","region":"North","overlord":"House Bolton"},{"name":"House Woolfield","coatOfArms":" Three woolsacks, white on purple, a white border","region":"The North","overlord":"House Bolton"},{"name":"House Wells (north)","coatOfArms":" Per fess cendrée and lozengy argent and vert, in chief five pellets","region":"North","overlord":"House Bolton"},{"name":"House Whitehill","coatOfArms":" A white pile inverted on indigo, an arch of 4-pointed stars above","words":" <i>Ever Higher</i>","seat":"Highpoint","region":"North","overlord":"House Bolton"},{"name":"House Crowl","coatOfArms":" Pily gules and sable","seat":"Deepdown","region":"North","overlord":"House Bolton"},{"name":"House Stane","coatOfArms":" A driftwood tree, bare and brown, on pale green","seat":"Driftwood Hall","region":"North","overlord":"House Bolton"},{"name":"House Myre","coatOfArms":" 10 nooses, 4-3-2-1, black on white with a border of blood","region":"Iron Islands","overlord":"House Harlaw"},{"name":"House Kenning of Harlaw","coatOfArms":" Sable, issuant from a cloud bank in chief the Storm God's hand cendrée with lightning flashing from its fingertip Or","region":"Iron Islands","overlord":"House Harlaw","cadetBranch":"House Kenning of Kayce"},{"name":"House Norridge","coatOfArms":" Azure, six arrows in bend sable heads flaming gules","region":"Reach","overlord":"House Tyrell"},{"name":"House Farwynd of the Lonely Light","coatOfArms":" Per fess wavy tenny and sable, a demi-torteaux gules issuant from the division surmounted by a longship sailing upon the division of the second","seat":"Lonely Light","currentLord":"Gylbert Farwynd","region":"Iron Islands","heir":"Gyles Farwynd","overlord":"House Greyjoy"},{"name":"House Sharp","region":"Iron Islands","overlord":"House Greyjoy"},{"name":"House Weaver","region":"Iron Islands"},{"name":"House Shepherd","region":"Iron Islands","overlord":"House Greyjoy"},{"name":"House Qoherys","coatOfArms":" A flaming red and yellow saltire between four white skulls, on a black field<br>(<i>Sable, a saltire rayonné gules, tipped or, between four skulls argent</i>)","seat":"Harrenhal","currentLord":" Extinct","region":"Riverlands","title":"Harrenhal","overlord":"House Tully","founder":"Quenton Qoherys","founded":"1 AC","died out":"37 AC"},{"name":"House Teague","coatOfArms":" A golden trident upright between two golden flanches, on a black field<br>(<i>Sable, between two flaunches a trident erect or</i>)","currentLord":" Extinct","region":"Riverlands","title":"King of the Trident","founder":"Torrence Teague","died out":"Battle of Six Kings"},{"name":"House Justman","coatOfArms":" Golden scales within a blue a double tressure, on a white field<br>(<i>Argent, a pair of balances or within a double-tressure azure</i>)","currentLord":" Extinct","region":"Riverlands","title":"King of the Trident","founder":"Benedict I Justman"},{"name":"House Towers of Harrenhal","coatOfArms":" Five black towers within a red and black double tressure, on a white field<br>(<i>Argent, five towers sable within a double-tressure, the outer gules and the inner of the second</i>)","seat":"Harrenhal","currentLord":" Extinct","region":"Riverlands","overlord":"House Tully"},{"name":"House Strong","coatOfArms":" A tripartite pale, blue, red, and green, on a white field<br>(<i>Argent, a pale tierced per pale azure, gules, and vert</i>)","seat":"Harrenhal","currentLord":" Extinct","region":"Riverlands","title":"Harrenhal","overlord":"House Tully","died out":"131 AC"},{"name":"House Keath","coatOfArms":" Quarterly of nine; a white fish on a grey field; a gold fish hook on a white field<br>(<i>Quarterly of nine,  first, third, fifth, seventh and ninth cendrée, a fish argent; second, fourth, sixth and eight argent, a fish-hook or</i>)","region":"Riverlands"},{"name":"House Lolliston","coatOfArms":" Three oaken barrels, on a white field<br>(<i>Argent, three oaken barrels proper</i>)","region":"Riverlands"},{"name":"House Donniger","coatOfArms":" A red sun rising from a grey-green sea, against a yellow sky<br>(<i>Per fesse wavy or and vert-cendrée, a demi-sun-in-splendour issuant from the line of division gules</i>)","region":"Vale","overlord":"House Arryn"},{"name":"House Netley","region":"Iron Islands","overlord":"House Greyjoy"},{"name":"House Terrick","coatOfArms":" Per saltire purple and gold, four hawks' heads countercharged<br>(<i>Per saltire purpure and or, four hawks' heads counterchanged</i>)","region":"Riverlands"},{"name":"House Goodbrother of Shatterstone","seat":"Shatterstone","currentLord":"Norne Goodbrother","region":"Iron Islands","overlord":"House Greyjoy"},{"name":"House Wode","coatOfArms":" Three white hedgehogs, on a yellow field<br>(<i>Or, three hedgehogs argent</i>)","words":" <i>Touch Me Not</i>","region":"Riverlands","overlord":"House Baelish of Harrenhal"},{"name":"House Elesham","coatOfArms":" A black star between an inverted stone-coloured double-pile, on a pink field<br>(<i>Carnation, a mullet sable between two piles issuant from base cendrée</i>)","seat":"the Paps","region":"Vale","overlord":"House Arryn"},{},{"name":"House Pryor","coatOfArms":" A partial eclipse, black moon over yellow sun, on a dusty pink field<br>(<i>Carnation, a sun-in-splendour or surmounted by a moon in her complement sable</i>)","seat":"Pebble","region":"Vale","overlord":"House Arryn"},{"name":"House Longthorpe","seat":"Longsister","currentLord":"Rolland Longthorpe","region":"Vale of Arryn","overlord":"House Sunderland"},{"name":"House Ruthermont","coatOfArms":" Five black starfish on a gold pale, on a field of pean<br>(<i>Pean, on a pale or five starfish sable</i>)","region":"Vale","overlord":"House Arryn"},{"name":"House Upcliff","coatOfArms":" A cresting sea-green wave, on a black field<br>(<i>Sable, a wave cresting vert</i>)","seat":"Witch Isle","region":"Vale","overlord":"House Arryn"},{"name":"House Torrent","seat":"Littlesister","currentLord":"Alesandor Torrent","region":"Vale of Arryn","title":" Lord of Littlesister","overlord":"House Sunderland"},{"name":"House Shett of Gull Tower","coatOfArms":" Three golden wings, bendwise, on a checkered white and black field<br>(<i>Chequy argent and sable, in bend three dexter wings elevated bendwise or</i>)","seat":"Gull Tower","currentLord":"Damon Shett","region":"Vale","title":" the Knight of Gull Tower","overlord":"House Royce"},{"name":"House Wydman","coatOfArms":" Five splintered lances, 3, 2, striped blue and white with blue pennons, on a yellow field, beneath a white chief bearing a red castle, a green viper, a  black broken wheel, a purple unicorn and a yellow lion<br>(<i>Or, five broken lances, 3, 2, striped azure and argent, pennons of the second, on a chief of the third, a wheel broken sable between, on the dexter, a castle gules and snake vert, and, on the sinister, a unicorn rampant purpure and lion rampant of the field</i>)","words":" <i>Right Conquers Might</i>","region":"Vale","overlord":"House Arryn"},{"name":"House Wagstaff","coatOfArms":" Five yellow mascles, on a green field<br>(<i>Vert, five mascles in fess or</i>)","region":"Stormlands","overlord":"House Baratheon"},{"name":"House Algood","coatOfArms":" A golden wreath, on a blue field with a gold border<br>(<i>Azure, a garland of laurel within a bordure or</i>)","region":"Westerlands","overlord":"House Lannister"},{"name":"House Garner","coatOfArms":" Three grey owls upon white plates, on a green field<br>(<i>Vert, three plates, each charged with an owl close affronté cendrée</i>)","region":"Westerlands","overlord":"House Lannister"},{"name":"House Appleton","coatOfArms":" Or, an apple tree eradicated proper fructed gules, quartered with argent, a gatehouse cendrée","seat":"Appleton","region":"Reach","overlord":"House Tyrell"},{"name":"House Doggett","coatOfArms":" Per bend, a white unicorn on a green field, a black raven on a white field<br>(<i>Per bend vert and argent, in sinister chief a unicorn rampant of the second, and in dexter base a raven closed sable</i>)","region":"Westerlands","overlord":"House Lannister"},{"name":"House Hamell","coatOfArms":" An erminois maunch, on a pink field with an erminois border<br>(<i>Carnation, a maunch within a bordure erminois</i>)","region":"Westerlands","overlord":"House Lannister"},{"name":"House Bridges","coatOfArms":" A black stone bridge with three arches upon a golden chief above three blue pallets on white","region":"Reach","overlord":"House Tyrell"},{"name":"House Cordwayner","coatOfArms":" Lozengny vert and or, a pair of boots sable","seat":"Hammerhal","region":"Reach","overlord":"House Tyrell"},{"name":"House Drox","coatOfArms":" Three black crossbows, on a gold field with a black border<br>(<i>Or, three crossbows within a bordure sable</i>)","region":"Westerlands","overlord":"House Lannister"},{"name":"House Graves","coatOfArms":" Green and white gyronny, a double-headed eagle counter-charged, gold beak and talons","region":"Reach","overlord":"House Tyrell"},{"name":"House Kidwell","coatOfArms":" Cendrée masoned sable, semy of ivy leaves vert","seat":"Ivy Hall","region":"Reach","overlord":"House Tyrell"},{"name":"House Bushy","coatOfArms":" A green fess embattled on white","region":"Reach","overlord":"House Tyrell"},{"name":"House Hastwyck","coatOfArms":" Barry olive and ivory","words":" <i>None so Dutiful</i>","region":"Reach","overlord":"House Tyrell"},{"name":"House Hutcheson","coatOfArms":" Or, two bendlets between in base dexter a hand pointing to chief sinister, and in chief sinister a sun in splendour gules","region":"Reach","overlord":"House Tyrell"},{"name":"House Lyberr","coatOfArms":" Per bend sinister: a grey cat's face on black, a brown jug on white","region":"Reach","overlord":"House Tyrell"},{"name":"House Lowther","coatOfArms":" A silver dolphin on a blue-green field","region":"Reach","overlord":"House Tyrell"},{"name":"House Middlebury","coatOfArms":" Quarterly, a black saltire on yellow, green and white diamonds","region":"Reach","overlord":"House Tyrell"},{"name":"House Redding","coatOfArms":" Gules, a flagon Or within a bordure chequy Or and argent","region":"Reach","overlord":"House Tyrell"},{"name":"House Oldflowers","coatOfArms":" Vert, ten hands couped argent surmounted by a bend sinister gules","region":"Reach","overlord":"House Tyrell"},{"name":"House Orme","coatOfArms":" Per fess sable and bendy Or and argent, in chief three harps in fess of the seocnd","region":"Reach","overlord":"House Tyrell"},{"name":"House Roxton","coatOfArms":" Bleu celeste, per saltire a chain of rings Or","seat":"Ring","region":"Reach","overlord":"House Tyrell","ancestralWeapon":"Orphan-Maker"},{"name":"House Pommingham","coatOfArms":" A red pomegranate on white, a double tressure red","region":"Reach","overlord":"House Tyrell"},{"name":"House Sloane","coatOfArms":" Per pale, white stars strewn on indigo, an orange sun on yellow","region":"Reach","overlord":"House Tyrell"},{"name":"House Woodwright","coatOfArms":" A red pall on a field of oak","region":"Reach","overlord":"House Tyrell"},{"name":"House Westbrook","coatOfArms":" Two green bars gemmel on gold","region":"Reach","overlord":"House Tyrell"},{"name":"House Yelshire","coatOfArms":" Barry vert and Or, on a chief sable a battering-ram proper headed Or","region":"Reach","overlord":"House Tyrell"},{"name":"House Horpe","coatOfArms":" Per chevron engrailed grey and bone, three death's head moths counterchanged<br>(<i>Per chevron reversed engrailed cendrée and argent, three death's head moths counterchanged</i>)","region":"Stormlands","overlord":"House Baratheon"},{"name":"House Kellington","coatOfArms":" A black book bound in bronze, locked, on a pale blue field<br>(<i>Azure, a locked book sable, edged and garnished tenné</i>)","region":"Stormlands","overlord":"House Baratheon"},{"name":"House Herston","coatOfArms":" A yellow rooster's head with red comb, within a white escutcheon, on a red field<br>(<i>Gules, on an escutcheon argent, a cock's head or, combed and wattled of the field</i>)","region":"Stormlands","overlord":"House Baratheon"},{"name":"House Peasebury","coatOfArms":" A green pea pod, burst open, on a white field, bordered by three rows of green peas<br>(<i>Argent, a pea pod open within a bordure of three rows of peas vert</i>)","seat":"Poddingfield","currentLord":"Robin Peasebury","region":"Stormlands","title":" Lord of Poddingfield","overlord":"House Baratheon of Dragonstone"},{"name":"House Musgood","coatOfArms":" Quarterly: A golden pavilion on a blue field, a green laurel crown on a white field<br>(<i>Quarterly, first and fourth, azure, a pavilion or, second and third, argent, a garland of laurel vert</i>)","region":"Stormlands","overlord":"House Baratheon"},{"name":"House Mertyns","coatOfArms":" A white great horned owl on a grey field<br>(<i>Cendrée, a great-horned owl close affronté argent</i>)","seat":"Mistwood","currentLord":"Mary Mertyns","region":"Stormlands","overlord":"House Baratheon"},{"name":"House Tudbury","coatOfArms":" A brown tortoise within a yellow lozenge, on a green field<br>(<i>Vert, on a lozenge or a tortoise tergiant tenné</i>)","region":"Stormlands","overlord":"House Baratheon"},{"name":"House Swygert","coatOfArms":" A white scroll with gold knobs, on a purple field within a white tressure<br>(<i>Purpure a scroll argent, knobbed or, within a tressure of the second</i>)","words":" <i>Truth Conquers</i>","region":"Stormlands","overlord":"House Baratheon"},{"name":"House Ladybright","region":"Dorne","overlord":"House Martell"},{"name":"House Hunt","coatOfArms":" Argent, a deer bound and slung on a pole fesswise tenny","region":"The Reach","overlord":"House Tarly"},{"name":"House Goodbrother of Orkmont","region":"Iron Islands","overlord":"House Greyjoy"},{"name":"House Cole","coatOfArms":" Ten black pellets, on a scarlet field<br>(<i>Gules, ten pellets, 4, 3, 2, 1</i>)","region":"Stormlands"},{"name":"House Rogers","coatOfArms":" Nine silver unicorns around a silver maze, on a black field<br>(<i>Sable, a maze surrounded by an orle of nine unicorns rampant argent</i>)","seat":"Amberly","region":"Stormlands","overlord":"House Baratheon"},{},{"name":"House Cox","seat":"Saltpans","currentLord":"Quincy Cox","region":"Riverlands","title":" Knight of Saltpans","overlord":"House Tully"},{"name":"House Dayne of High Hermitage","seat":"High Hermitage","currentLord":"Gerold Dayne","region":"Dorne","title":" the Knight of High Hermitage","overlord":"House Dayne"},{"name":"House Lannister of Lannisport","seat":"Lannisport","region":"Westerlands","overlord":"House Lannister"},{"name":"House Arryn of Gulltown","seat":"Gulltown","region":"Vale","overlord":"House Arryn"},{"name":"House Clifton","currentLord":"Gareth Clifton","region":"Westerlands","overlord":"House Farman"},{"name":"House Drinkwater","region":"Dorne","overlord":"House Yronwood"},{},{},{"name":"House Westford","coatOfArms":" A black dog on blue","currentLord":"Mors Westford","region":"Westerlands","overlord":"House Lannister"},{"name":"House Forrester","coatOfArms":" an ironwood tree outline with a sword outline drawn inside it, pointing down. (Telltale)","words":" <i>Iron from Ice</i> (Telltale)","seat":"Ironrath","currentLord":"Rodrik Forrester","region":"The North","overlord":"House Glover","founder":"Gerhard Forrester"},{"name":"House Wells (Dorne)","region":"Dorne","overlord":"House Martell"},{},{},{"name":"House Thenn","coatOfArms":" Argent, a sun in splendour gules","currentLord":"Sigorn","region":"North","title":" Magnar of Thenn","founder":" Sigorn","founded":"300 AC"},{},{},{},{},{"name":"House Peat","region":"The Neck","overlord":"House Reed"},{"name":"House Tyrell of Brightwater Keep","seat":"Brightwater Keep","currentLord":"Garlan Tyrell","region":"The Reach","title":"Brightwater Keep","overlord":"House Tyrell of Highgarden","founder":"Garlan Tyrell","founded":"299 AC"},{"name":"House Cray","region":"The Neck","overlord":"House Reed"},{"name":"House Quagg","region":"The Neck","overlord":"House Reed"},{"name":"House Boggs (north)","region":"North","overlord":"House Reed"},{"name":"House Blackmyre","region":"The Neck","overlord":"House Reed"},{},{"name":"House Bole","region":"The North","overlord":"House Glover"},{"name":"House Woods","region":"The North","overlord":"House Glover"},{"name":"House Greengood","region":"The Neck","overlord":"House Reed"},{},{},{},{},{},{},{},{},{},{},{},{},{},{},{},{},{"name":"House Strickland","currentLord":"Harry Strickland"},{},{},{"name":"House Branch","region":"The North","overlord":"House Glover"},{},{"name":"House Redbeard","currentLord":"Gerrick Kingsblood","region":"Wall","title":" King of the Wildlings","overlord":"House Baratheon of Dragonstone","founder":" Gerrick Kingsblood","founded":"300 AC"},{"name":"House Mandrake","coatOfArms":" unknown","words":" unknown","seat":" unknown","region":" unknown"},{"name":"House Harlaw of Grey Garden","coatOfArms":" Quartered: a silver scythe on black, a peacock on cream","seat":"Grey Garden","currentLord":"Harras Harlaw","region":"Iron Islands","title":" Knight of Grey Garden<br>Lord of Greyshield","overlord":"House Harlaw"},{"name":"House Lannister of Darry","coatOfArms":" Quarterly, a gold lion on a red field; a black plowman on a brown field<br>(<i>Quarterly, first and fourth gules a lion rampant or (for Lannister), second and third tenné a plowman sable (for Darry)</i>)","seat":"Darry","currentLord":"Lancel Lannister","region":"Riverlands","title":" Lord of Darry","overlord":"House Baelish of Harrenhal","founder":"Lancel Lannister","founded":"299 AC"},{},{"name":"House Ashwood","region":"North","overlord":"House Bolton"},{},{},{"name":"House Holt (north)","region":"North","overlord":"House Bolton"},{"name":"House Long","region":"North","overlord":"House Bolton"},{"name":"House Chambers","region":"Riverlands"},{"name":"House Perryn","region":"Riverlands"},{"name":"House Bigglestone","region":"Riverlands"},{"name":"Norren (House Mooton)","title":"Maester","allegiance":"House Mooton","born":"108 AC","book(s)":"The Princess and the Queen"},{"name":"House Darke","region":"Crownlands"},{},{},{"name":"House Ironmaker","currentLord":"Erik Ironmaker","region":"Iron Islands","overlord":"House Greyjoy"},{"name":"House Harlaw of Harlaw Hall","coatOfArms":" Per bend black and silver, two scythes counterchanged","seat":"Harlaw Hall","currentLord":"Sigfryd Harlaw","region":"Iron Islands","title":" Master of Harlaw Hall","overlord":"House Harlaw"},{},{},{"name":"House Durrandon","coatOfArms":" A black crowned stag, on a gold field<br>(<i>Or, a stag salient, crowned, sable</i>)","words":" <i>Ours is the Fury</i>","seat":"Storm's End","region":"The Stormlands","title":"Storm King","heir":" Extinct","cadetBranch":"House Baratheon","founder":"Durran","founded":"Age of Heroes","died out":"1 AC"},{},{},{},{},{},{"name":"House Harlaw of the Tower of Glimmering","coatOfArms":" The Harlaw scythe girdled within an embattled border.","seat":"Tower of Glimmering","currentLord":"Hotho Harlaw","region":"Iron Islands","title":" Master of the Tower of Glimmering","overlord":"House Harlaw"},{"name":"House Grey","region":"Riverlands"},{"name":"House Goode","coatOfArms":" Unknown","currentLord":" Extinct?","region":" Unknown"},{"name":"House Harlaw of Harridan Hill","coatOfArms":" the Harlaw scythe on a pale blue field","seat":"Harridan Hill","currentLord":"Boremund Harlaw","region":"Iron Islands","title":" Master of Harridan Hill","overlord":"House Harlaw"},{},{"name":"House Blackberry","region":"crownlands","overlord":"House Baratheon of Dragonstone"},{"name":"House Cupps","seat":" Unknown","currentLord":" Unknown"},{"name":"House Hawthorne","coatOfArms":" A ring of black thorns and a ring of pink flowers, interlocked, on a green field<br>(<i>Vert, two interlocking annulets, one composed of thorns sable, the other of flowers carnation</i>)","region":"Westerlands","overlord":"House Lannister"},{},{},{"name":"House Shell (Vale)","region":"the Vale","title":"King of the Fingers","died out":"Andal invasion"},{"name":"House Brightstone","region":"the Vale","title":"King of the Fingers","died out":"Andal invasion"},{"name":"House Ryder","seat":"Rills","currentLord":" Possibly extinct","region":"the North","overlord":"House Stark"},{"name":"House Dryland","region":"Dorne","title":"King of the Brimstone","overlord":" none","died out":"Rhoynar migration"},{"name":"House Fisher of the Stony Shore","seat":"Stony Shore","currentLord":" Possibly extinct","region":"the North","overlord":"House Stark"},{"name":"House Flint of Breakstone Hill","seat":"Breakstone Hill","currentLord":" Possibly extinct","region":"the North","overlord":"House Stark"},{"name":"House Hook","seat":" Extinct","region":"Riverlands"},{"name":"House Amber","currentLord":" Extinct","region":"the North"},{"name":"House Greenwood","currentLord":" Extinct","region":"the North"},{"name":"House Frost","currentLord":" Extinct","region":"the North"},{"name":"House Towers (north)","currentLord":" Extinct","region":"North"},{},{},{"name":"House Nutt","region":"Riverlands"},{},{"name":"House Sweet","overlord":"House Baratheon of Dragonstone"},{"name":"House Briar","region":"Dorne","title":"High King of Dorne","overlord":" none"},{},{"name":"House Lake (Dorne)","region":"Dorne","title":"High King of Dorne","overlord":" none"},{"name":"House Brook","region":"Dorne","title":"High King of Dorne","overlord":" none"},{"name":"House Hull","region":"Dorne","title":"High King of Dorne","overlord":" none"},{},{"name":"House Holt (Dorne)","region":"Dorne","title":"High King of Dorne","overlord":" none"},{"name":"House Brownhill","region":"Dorne","title":"High King of Dorne","overlord":" none"},{"name":"House of the Undying servitor","allegiance":"Undying Ones","race":"Qartheen","book(s)":"A Clash of Kings"},{"name":"House Shell (Dorne)","region":"Dorne","title":"High King of Dorne","overlord":" none"},{},{"name":"House Wade","region":"Dorne","title":"High King of Dorne","overlord":" none"},{"name":"House Belgrave","coatOfArms":" unknown","currentLord":" unknown","region":" unknown"},{},{"name":"House Penny","coatOfArms":" Unknown","region":" Unknown"},{},{},{},{},{"name":"House Kyndall","region":"Westerlands","overlord":"House Lannister"},{"name":"House Branfield","seat":"Ironrath","currentLord":"Malcolm Branfield","region":"North"},{"name":"House Shett of Gulltown","coatOfArms":" Nine white seagulls on a field of brown<br>(<i>Tenné, nine seagulls argent, 3, 3, 2, 1</i>)","seat":"Gulltown","region":"Vale","overlord":"House Grafton"},{"name":"House Breakstone","coatOfArms":" A red sledge","region":"Vale"},{},{"name":"House Darkwood","region":"Crownlands"},{"name":"House Longwaters","region":"Crownlands","overlord":"House Baratheon of King's Landing"},{},{"name":"House Dargood","region":"Crownlands"},{},{},{"name":"House Lipps","coatOfArms":" Two large pink lips, on a dark blue field<br>(<i>Azure, a pair of lips carnation</i>)","region":"Vale","overlord":"House Arryn"},{"name":"House Glenmore","seat":"Rillwater Crossing","region":"North"},{"name":"House Heddle","region":"Riverlands","overlord":"House Baelish of Harrenhal"},{"name":"House Lanny","region":"Westerlands"},{"name":"House Lannett","region":"Westerlands"},{"name":"House Lantell","region":"Westerlands"},{},{"name":"House Harlton","coatOfArms":" A silver tree on green","seat":"Castlewood","region":"Riverlands","overlord":"House Tully"},{"name":"House Sarwyck","coatOfArms":" A broken silver sword on red","seat":"Riverspring","region":"Westerlands","overlord":"House Lannister"},{},{},{},{"name":"The House of Black and White","episode #":"5","airdate":" April 19th, 2015","director":"Michael Slovis"},{},{},{},{},{},{},{"name":"House Bolton of Winterfell","coatOfArms":" A red flayed man on pink de sang","words":" <i>Our Blades are Sharp</i>","seat":"Winterfell","currentLord":"Ramsay Bolton","region":"north","title":" Lord of Winterfell","overlord":"House Bolton","founded":"300 AC"},{"name":"House Pemford","region":"riverlands","overlord":"House Tully"}],"createdAt":"2016-03-03T19:28:56.836Z"}
